{"params":{"formFactor":"PHONE","url":true,"date":"15.02.2022"},"metrics":[{"url":"https://allegro.pl/","CLS":{"histogram":[99.15,0.58,0.27],"p75":"0.00","rank":"good"},"FCP":{"histogram":[90.26,6,3.74],"p75":1141,"rank":"good"},"FID":{"histogram":[90.93,7.36,1.72],"p75":35,"rank":"good"},"LCP":{"histogram":[91.53,5.22,3.25],"p75":1487,"rank":"good"}},{"url":"https://m.ceneo.pl/","CLS":{"histogram":[75.91,10.68,13.41],"p75":"0.09","rank":"good"},"FCP":{"histogram":[87.72,7.33,4.95],"p75":1210,"rank":"good"},"FID":{"histogram":[84.17,12.29,3.53],"p75":62,"rank":"good"},"LCP":{"histogram":[83.97,10.16,5.87],"p75":1986,"rank":"good"}},{"url":"https://www.mediaexpert.pl/","CLS":{"histogram":[89.01,7.42,3.57],"p75":"0.07","rank":"good"},"FCP":{"histogram":[89.58,6.65,3.77],"p75":1148,"rank":"good"},"FID":{"histogram":[81.05,12.56,6.39],"p75":67,"rank":"good"},"LCP":{"histogram":[88.39,7.39,4.22],"p75":1728,"rank":"good"}},{"url":"https://m.euro.com.pl/","CLS":{"histogram":[36.19,38.04,25.76],"p75":"0.26","rank":"poor"},"FCP":{"histogram":[84.69,9.87,5.43],"p75":1379,"rank":"good"},"FID":{"histogram":[93.23,5.94,0.84],"p75":22,"rank":"good"},"LCP":{"histogram":[71.21,19.5,9.29],"p75":2684,"rank":"average"}},{"url":"https://www.empik.com/","CLS":{"histogram":[42.08,37.43,20.49],"p75":"0.23","rank":"average"},"FCP":{"histogram":[72.52,18.46,9.02],"p75":1911,"rank":"average"},"FID":{"histogram":[64.05,19.56,16.39],"p75":185,"rank":"average"},"LCP":{"histogram":[57.15,19.71,23.14],"p75":3825,"rank":"average"}},{"url":"https://www.doz.pl/","CLS":{"histogram":[98.77,0.62,0.61],"p75":"0.01","rank":"good"},"FCP":{"histogram":[87.2,7.84,4.96],"p75":1225,"rank":"good"},"FID":{"histogram":[92.59,5.52,1.89],"p75":33,"rank":"good"},"LCP":{"histogram":[86.34,8.77,4.9],"p75":1860,"rank":"good"}},{"url":"https://www.eobuwie.com.pl/","CLS":{"histogram":[73.52,25.38,1.1],"p75":"0.10","rank":"good"},"FCP":{"histogram":[89.04,7.09,3.87],"p75":1137,"rank":"good"},"FID":{"histogram":[92.54,6.66,0.8],"p75":31,"rank":"good"},"LCP":{"histogram":[53.86,30.14,16],"p75":3397,"rank":"average"}},{"url":"https://www.amazon.pl/","CLS":{"histogram":[97.89,0.47,1.63],"p75":"0.00","rank":"good"},"FCP":{"histogram":[88.85,6.89,4.26],"p75":1176,"rank":"good"},"FID":{"histogram":[92.9,6.15,0.95],"p75":25,"rank":"good"},"LCP":{"histogram":[92.99,4.48,2.53],"p75":1356,"rank":"good"}},{"url":"https://m.aliexpress.com/","CLS":{"histogram":[77.59,14.38,8.03],"p75":"0.07","rank":"good"},"FCP":{"histogram":[87.18,8.18,4.64],"p75":1196,"rank":"good"},"FID":{"histogram":[93.85,4.79,1.36],"p75":18,"rank":"good"},"LCP":{"histogram":[74.91,15.22,9.86],"p75":2522,"rank":"average"}},{"url":"https://www.castorama.pl/","CLS":{"histogram":[89.26,1.05,9.69],"p75":"0.01","rank":"good"},"FCP":{"histogram":[86.1,8.75,5.15],"p75":1311,"rank":"good"},"FID":{"histogram":[88.31,7.71,3.98],"p75":33,"rank":"good"},"LCP":{"histogram":[76.18,15.74,8.08],"p75":2448,"rank":"good"}},{"url":"https://allegrolokalnie.pl/","CLS":{"histogram":[93.49,5.66,0.85],"p75":"0.02","rank":"good"},"FCP":{"histogram":[89.85,6.73,3.42],"p75":1173,"rank":"good"},"FID":{"histogram":[93.15,5.19,1.66],"p75":25,"rank":"good"},"LCP":{"histogram":[60.3,25.99,13.71],"p75":3157,"rank":"average"}},{"url":"https://www.zalando.pl/","CLS":{"histogram":[95.43,2.87,1.7],"p75":"0.00","rank":"good"},"FCP":{"histogram":[88.98,7.43,3.59],"p75":1276,"rank":"good"},"FID":{"histogram":[84.81,10.7,4.49],"p75":54,"rank":"good"},"LCP":{"histogram":[88.76,7.68,3.56],"p75":1851,"rank":"good"}},{"url":"https://m.olx.pl/","CLS":{"histogram":[34.4,24.87,40.73],"p75":"0.36","rank":"poor"},"FCP":{"histogram":[67.69,20.96,11.35],"p75":2081,"rank":"average"},"FID":{"histogram":[61.71,17.1,21.19],"p75":239,"rank":"average"},"LCP":{"histogram":[67.3,19.82,12.87],"p75":2911,"rank":"average"}},{"url":"https://m.alza.cz/","CLS":{"histogram":[76.07,8.47,15.46],"p75":"0.09","rank":"good"},"FCP":{"histogram":[81.99,12.95,5.06],"p75":1545,"rank":"good"},"FID":{"histogram":[86.06,11.35,2.59],"p75":48,"rank":"good"},"LCP":{"histogram":[69.63,21.09,9.28],"p75":2743,"rank":"average"}},{"url":"https://www.mall.cz/","CLS":{"histogram":[21.47,19.49,59.04],"p75":"0.43","rank":"poor"},"FCP":{"histogram":[82.23,13.03,4.74],"p75":1579,"rank":"good"},"FID":{"histogram":[56.7,15.89,27.42],"p75":348,"rank":"poor"},"LCP":{"histogram":[71.49,21.07,7.45],"p75":2653,"rank":"average"}},{"url":"https://www.rohlik.cz/","CLS":{"histogram":[51.38,5.28,43.33],"p75":"0.50","rank":"poor"},"FCP":{"histogram":[52.4,27.68,19.91],"p75":2734,"rank":"average"},"FID":{"histogram":[64.21,20.09,15.7],"p75":175,"rank":"average"},"LCP":{"histogram":[51.54,28.53,19.93],"p75":3667,"rank":"average"}},{"url":"https://www.czc.cz/","CLS":{"histogram":[94.49,2.96,2.55],"p75":"0.00","rank":"good"},"FCP":{"histogram":[92.89,4.71,2.4],"p75":950,"rank":"good"},"FID":{"histogram":[92.9,5.46,1.63],"p75":27,"rank":"good"},"LCP":{"histogram":[90.46,6.62,2.92],"p75":1612,"rank":"good"}},{"url":"https://m.alza.sk/","CLS":{"histogram":[77.75,8.09,14.16],"p75":"0.08","rank":"good"},"FCP":{"histogram":[82.56,11.18,6.26],"p75":1485,"rank":"good"},"FID":{"histogram":[88.45,9.74,1.81],"p75":38,"rank":"good"},"LCP":{"histogram":[73.21,17.86,8.93],"p75":2584,"rank":"average"}},{"url":"https://www.mall.sk/","CLS":{"histogram":[24.45,18.81,56.74],"p75":"0.42","rank":"poor"},"FCP":{"histogram":[84.13,11.63,4.24],"p75":1505,"rank":"good"},"FID":{"histogram":[59.29,14.88,25.82],"p75":315,"rank":"poor"},"LCP":{"histogram":[74.07,19.26,6.67],"p75":2543,"rank":"average"}},{"url":"https://tesco.sk/","CLS":{"histogram":[65.11,24.96,9.93],"p75":"0.16","rank":"average"},"FCP":{"histogram":[46.72,25.49,27.79],"p75":3355,"rank":"poor"},"FID":{"histogram":[82.91,10.48,6.61],"p75":49,"rank":"good"},"LCP":{"histogram":[45.93,24.37,29.69],"p75":4561,"rank":"poor"}},{"url":"https://www.notino.sk/","CLS":{"histogram":[93.17,3.83,3],"p75":"0.01","rank":"good"},"FCP":{"histogram":[84.37,10.26,5.37],"p75":1399,"rank":"good"},"FID":{"histogram":[88.63,9.97,1.4],"p75":41,"rank":"good"},"LCP":{"histogram":[88.99,7.26,3.74],"p75":1678,"rank":"good"}},{"url":"https://www.amazon.de/","CLS":{"histogram":[97.08,1.31,1.62],"p75":"0.00","rank":"good"},"FCP":{"histogram":[90.98,5.92,3.11],"p75":1074,"rank":"good"},"FID":{"histogram":[92.22,6.49,1.29],"p75":34,"rank":"good"},"LCP":{"histogram":[93.3,4.29,2.4],"p75":1304,"rank":"good"}},{"url":"https://www.otto.de/","CLS":{"histogram":[74.52,13.35,12.14],"p75":"0.10","rank":"good"},"FCP":{"histogram":[92.84,4.58,2.57],"p75":901,"rank":"good"},"FID":{"histogram":[85.99,11.65,2.35],"p75":55,"rank":"good"},"LCP":{"histogram":[85.62,10.2,4.17],"p75":1958,"rank":"good"}},{"url":"https://www.zalando.de/","CLS":{"histogram":[91.36,4.57,4.07],"p75":"0.00","rank":"good"},"FCP":{"histogram":[79.03,15.58,5.39],"p75":1718,"rank":"good"},"FID":{"histogram":[79.75,14.42,5.83],"p75":76,"rank":"good"},"LCP":{"histogram":[82.15,12.13,5.72],"p75":2175,"rank":"good"}},{"url":"https://www.mediamarkt.de/","CLS":{"histogram":[74.29,14.48,11.24],"p75":"0.12","rank":"average"},"FCP":{"histogram":[84.33,10.9,4.78],"p75":1441,"rank":"good"},"FID":{"histogram":[54.5,18.75,26.75],"p75":328,"rank":"poor"},"LCP":{"histogram":[81.57,12.02,6.41],"p75":2121,"rank":"good"}},{"url":"https://www.lidl.de/","CLS":{"histogram":[97.32,1.82,0.86],"p75":"0.00","rank":"good"},"FCP":{"histogram":[63.93,24.72,11.34],"p75":2196,"rank":"average"},"FID":{"histogram":[93.34,5.27,1.38],"p75":21,"rank":"good"},"LCP":{"histogram":[71.68,19.86,8.46],"p75":2653,"rank":"average"}},{"url":"https://www.ebay.de/","CLS":{"histogram":[87.18,11.78,1.03],"p75":"0.02","rank":"good"},"FCP":{"histogram":[88.81,7.59,3.6],"p75":1189,"rank":"good"},"FID":{"histogram":[89.51,8.41,2.08],"p75":32,"rank":"good"},"LCP":{"histogram":[87.15,9.01,3.84],"p75":1836,"rank":"good"}},{"url":"https://www.bol.com/nl/nl/","CLS":{"histogram":[82.82,15.09,2.09],"p75":"0.01","rank":"good"},"FCP":{"histogram":[92.36,5.28,2.36],"p75":1014,"rank":"good"},"FID":{"histogram":[87.05,9.05,3.89],"p75":48,"rank":"good"},"LCP":{"histogram":[92.24,5.53,2.23],"p75":1538,"rank":"good"}},{"url":"https://rozetka.com.ua/","CLS":{"histogram":[31.86,16.24,51.9],"p75":"0.29","rank":"poor"},"FCP":{"histogram":[81.01,11.55,7.45],"p75":1546,"rank":"good"},"FID":{"histogram":[80.06,11.71,8.23],"p75":66,"rank":"good"},"LCP":{"histogram":[42.4,27.38,30.23],"p75":4428,"rank":"poor"}},{"url":"https://m.olx.ua/","CLS":{"histogram":[35.98,19.56,44.45],"p75":"0.34","rank":"poor"},"FCP":{"histogram":[67.19,20.06,12.75],"p75":2147,"rank":"average"},"FID":{"histogram":[60.71,15.03,24.26],"p75":287,"rank":"average"},"LCP":{"histogram":[67.52,19.2,13.28],"p75":2941,"rank":"average"}},{"url":"https://prom.ua/","CLS":{"histogram":[78,10.35,11.65],"p75":"0.07","rank":"good"},"FCP":{"histogram":[77.89,14.68,7.43],"p75":1703,"rank":"good"},"FID":{"histogram":[74.47,10.31,15.22],"p75":102,"rank":"average"},"LCP":{"histogram":[67.76,20.2,12.04],"p75":2885,"rank":"average"}},{"url":"https://epicentrk.ua/","CLS":{"histogram":[23.08,1.28,75.63],"p75":"0.97","rank":"poor"},"FCP":{"histogram":[53.48,23.31,23.21],"p75":2904,"rank":"average"},"FID":{"histogram":[42.5,16.07,41.43],"p75":715,"rank":"poor"},"LCP":{"histogram":[31.4,33.29,35.3],"p75":4988,"rank":"poor"}},{"url":"https://merxu.com/pl/","CLS":{"histogram":[89.43,2.26,8.32],"p75":"0.00","rank":"good"},"FCP":{"histogram":[67.88,20.99,11.12],"p75":2175,"rank":"average"},"FID":{"histogram":[81.68,10.03,8.29],"p75":54,"rank":"good"},"LCP":{"histogram":[74.09,16.88,9.03],"p75":2634,"rank":"average"}},{"url":"https://www.x-kom.pl/","CLS":{"histogram":[25.14,15.55,59.31],"p75":"0.59","rank":"poor"},"FCP":{"histogram":[79.73,12.09,8.19],"p75":1625,"rank":"good"},"FID":{"histogram":[55.17,14.82,30.01],"p75":445,"rank":"poor"},"LCP":{"histogram":[60.65,23.01,16.35],"p75":3281,"rank":"average"}},{"url":"https://www.morele.net/","CLS":{"histogram":[98.47,0.75,0.78],"p75":"0.00","rank":"good"},"FCP":{"histogram":[85.9,8.96,5.14],"p75":1276,"rank":"good"},"FID":{"histogram":[93.23,5.61,1.17],"p75":27,"rank":"good"},"LCP":{"histogram":[89.78,7.04,3.18],"p75":1580,"rank":"good"}}]}