{"params":{"formFactor":"PHONE","url":true,"date":"27.04.2022"},"metrics":[{"url":"https://allegro.pl/","CLS":{"histogram":[98.89,0.3,0.81],"p75":"0.00","rank":"good"},"FCP":{"histogram":[91.96,5.15,2.89],"p75":1055,"rank":"good"},"FID":{"histogram":[90.34,8.03,1.63],"p75":35,"rank":"good"},"LCP":{"histogram":[92.27,4.85,2.88],"p75":1443,"rank":"good"}},{"url":"https://m.ceneo.pl/","CLS":{"histogram":[60.88,30.8,8.32],"p75":"0.11","rank":"average"},"FCP":{"histogram":[89.66,6.62,3.72],"p75":1161,"rank":"good"},"FID":{"histogram":[81.6,13.66,4.74],"p75":73,"rank":"good"},"LCP":{"histogram":[84.31,10.53,5.16],"p75":2002,"rank":"good"}},{"url":"https://www.mediaexpert.pl/","CLS":{"histogram":[88.53,7.99,3.49],"p75":"0.07","rank":"good"},"FCP":{"histogram":[90.03,6.49,3.48],"p75":1165,"rank":"good"},"FID":{"histogram":[75.77,13.32,10.9],"p75":94,"rank":"good"},"LCP":{"histogram":[87.13,8.6,4.26],"p75":1862,"rank":"good"}},{"url":"https://m.euro.com.pl/","CLS":{"histogram":[53.15,44.68,2.17],"p75":"0.16","rank":"average"},"FCP":{"histogram":[85.03,9.79,5.18],"p75":1357,"rank":"good"},"FID":{"histogram":[92.61,6.32,1.07],"p75":24,"rank":"good"},"LCP":{"histogram":[75.83,16.45,7.72],"p75":2465,"rank":"good"}},{"url":"https://www.empik.com/","CLS":{"histogram":[55.17,39.47,5.36],"p75":"0.18","rank":"average"},"FCP":{"histogram":[75.06,16.18,8.76],"p75":1814,"rank":"average"},"FID":{"histogram":[63.01,19.78,17.21],"p75":194,"rank":"average"},"LCP":{"histogram":[56.56,20.56,22.87],"p75":3774,"rank":"average"}},{"url":"https://www.doz.pl/","CLS":{"histogram":[99.23,0.32,0.45],"p75":"0.01","rank":"good"},"FCP":{"histogram":[89.88,6.35,3.77],"p75":1134,"rank":"good"},"FID":{"histogram":[91.61,6.2,2.2],"p75":33,"rank":"good"},"LCP":{"histogram":[89.33,7.03,3.64],"p75":1703,"rank":"good"}},{"url":"https://www.eobuwie.com.pl/","CLS":{"histogram":[75.35,24.34,0.31],"p75":"0.09","rank":"good"},"FCP":{"histogram":[93.73,3.98,2.28],"p75":901,"rank":"good"},"FID":{"histogram":[91.62,7.37,1.02],"p75":35,"rank":"good"},"LCP":{"histogram":[56.62,29.15,14.22],"p75":3252,"rank":"average"}},{"url":"https://www.amazon.pl/","CLS":{"histogram":[96.2,1.43,2.37],"p75":"0.00","rank":"good"},"FCP":{"histogram":[89.32,6.66,4.02],"p75":1161,"rank":"good"},"FID":{"histogram":[91.54,7.26,1.2],"p75":30,"rank":"good"},"LCP":{"histogram":[92.05,4.96,3],"p75":1403,"rank":"good"}},{"url":"https://m.aliexpress.com/","CLS":{"histogram":[58.79,17.71,23.5],"p75":"0.23","rank":"average"},"FCP":{"histogram":[91.37,5.13,3.5],"p75":860,"rank":"good"},"FID":{"histogram":[93.13,5.24,1.63],"p75":17,"rank":"good"},"LCP":{"histogram":[76.37,13.65,9.97],"p75":2427,"rank":"good"}},{"url":"https://www.castorama.pl/","CLS":{"histogram":[89.24,1.22,9.55],"p75":"0.01","rank":"good"},"FCP":{"histogram":[89.06,6.81,4.14],"p75":1172,"rank":"good"},"FID":{"histogram":[88.67,7.49,3.85],"p75":32,"rank":"good"},"LCP":{"histogram":[78.04,14.62,7.33],"p75":2341,"rank":"good"}},{"url":"https://allegrolokalnie.pl/","CLS":{"histogram":[89.32,9.42,1.26],"p75":"0.05","rank":"good"},"FCP":{"histogram":[92.2,5.37,2.43],"p75":1083,"rank":"good"},"FID":{"histogram":[92.91,5.16,1.93],"p75":23,"rank":"good"},"LCP":{"histogram":[63.9,24.55,11.56],"p75":3002,"rank":"average"}},{"url":"https://www.zalando.pl/","CLS":{"histogram":[95.41,2.52,2.07],"p75":"0.00","rank":"good"},"FCP":{"histogram":[88.67,7,4.33],"p75":1211,"rank":"good"},"FID":{"histogram":[85.69,10.17,4.14],"p75":51,"rank":"good"},"LCP":{"histogram":[90.66,6.48,2.86],"p75":1744,"rank":"good"}},{"url":"https://m.olx.pl/","CLS":{"histogram":[46.13,19.93,33.94],"p75":"0.33","rank":"poor"},"FCP":{"histogram":[69.31,21.09,9.6],"p75":2012,"rank":"average"},"FID":{"histogram":[54,13.78,32.22],"p75":541,"rank":"poor"},"LCP":{"histogram":[70,19.87,10.13],"p75":2730,"rank":"average"}},{"url":"https://m.alza.cz/","CLS":{"histogram":[77.4,9.64,12.96],"p75":"0.09","rank":"good"},"FCP":{"histogram":[91.76,5.4,2.84],"p75":1060,"rank":"good"},"FID":{"histogram":[86.55,10.5,2.95],"p75":46,"rank":"good"},"LCP":{"histogram":[76.06,16.45,7.49],"p75":2445,"rank":"good"}},{"url":"https://www.mall.cz/","CLS":{"histogram":[34.1,18.82,47.08],"p75":"0.43","rank":"poor"},"FCP":{"histogram":[82.47,13.34,4.19],"p75":1580,"rank":"good"},"FID":{"histogram":[57.05,15.17,27.78],"p75":363,"rank":"poor"},"LCP":{"histogram":[78.38,16.34,5.28],"p75":2362,"rank":"good"}},{"url":"https://www.rohlik.cz/","CLS":{"histogram":[60.65,6.49,32.86],"p75":"0.50","rank":"poor"},"FCP":{"histogram":[21.1,41.22,37.68],"p75":3572,"rank":"poor"},"FID":{"histogram":[59.96,19.74,20.3],"p75":224,"rank":"average"},"LCP":{"histogram":[41.31,35.32,23.38],"p75":3900,"rank":"average"}},{"url":"https://www.czc.cz/","CLS":{"histogram":[94.78,2.5,2.72],"p75":"0.00","rank":"good"},"FCP":{"histogram":[93.55,4.49,1.96],"p75":944,"rank":"good"},"FID":{"histogram":[90.04,6.59,3.38],"p75":30,"rank":"good"},"LCP":{"histogram":[91.48,5.99,2.54],"p75":1545,"rank":"good"}},{"url":"https://m.alza.sk/","CLS":{"histogram":[78.86,9.4,11.74],"p75":"0.08","rank":"good"},"FCP":{"histogram":[92.08,5.1,2.82],"p75":1040,"rank":"good"},"FID":{"histogram":[88.08,9.56,2.36],"p75":38,"rank":"good"},"LCP":{"histogram":[77.71,15.41,6.88],"p75":2361,"rank":"good"}},{"url":"https://www.mall.sk/","CLS":{"histogram":[36.84,17.85,45.32],"p75":"0.43","rank":"poor"},"FCP":{"histogram":[84.58,11.7,3.72],"p75":1512,"rank":"good"},"FID":{"histogram":[61.53,13.9,24.57],"p75":292,"rank":"average"},"LCP":{"histogram":[80.5,14.78,4.72],"p75":2258,"rank":"good"}},{"url":"https://tesco.sk/","CLS":{"histogram":[72.73,18.66,8.62],"p75":"0.11","rank":"average"},"FCP":{"histogram":[46.34,25.77,27.89],"p75":3349,"rank":"poor"},"FID":{"histogram":[82.27,9.94,7.79],"p75":52,"rank":"good"},"LCP":{"histogram":[42.24,25.81,31.94],"p75":4763,"rank":"poor"}},{"url":"https://www.notino.sk/","CLS":{"histogram":[93.39,3.77,2.85],"p75":"0.01","rank":"good"},"FCP":{"histogram":[85.61,9.69,4.7],"p75":1356,"rank":"good"},"FID":{"histogram":[88.15,10.18,1.67],"p75":41,"rank":"good"},"LCP":{"histogram":[89.97,6.73,3.3],"p75":1638,"rank":"good"}},{"url":"https://www.amazon.de/","CLS":{"histogram":[97.38,1.09,1.53],"p75":"0.00","rank":"good"},"FCP":{"histogram":[92.32,5.14,2.54],"p75":1023,"rank":"good"},"FID":{"histogram":[91.78,6.88,1.34],"p75":37,"rank":"good"},"LCP":{"histogram":[92.6,4.69,2.71],"p75":1320,"rank":"good"}},{"url":"https://www.otto.de/","CLS":{"histogram":[77.09,13.33,9.58],"p75":"0.09","rank":"good"},"FCP":{"histogram":[94.01,4.03,1.96],"p75":865,"rank":"good"},"FID":{"histogram":[87.5,10.8,1.7],"p75":51,"rank":"good"},"LCP":{"histogram":[85.37,10.56,4.07],"p75":1964,"rank":"good"}},{"url":"https://www.zalando.de/","CLS":{"histogram":[92.42,3.81,3.77],"p75":"0.00","rank":"good"},"FCP":{"histogram":[79.95,15.25,4.8],"p75":1665,"rank":"good"},"FID":{"histogram":[79.82,14.59,5.59],"p75":75,"rank":"good"},"LCP":{"histogram":[83.61,11.45,4.94],"p75":2096,"rank":"good"}},{"url":"https://www.mediamarkt.de/","CLS":{"histogram":[70.17,15.63,14.2],"p75":"0.16","rank":"average"},"FCP":{"histogram":[88,8.21,3.79],"p75":1220,"rank":"good"},"FID":{"histogram":[48.93,19.33,31.74],"p75":428,"rank":"poor"},"LCP":{"histogram":[79.64,11.64,8.73],"p75":2178,"rank":"good"}},{"url":"https://www.lidl.de/","CLS":{"histogram":[93.32,4.13,2.56],"p75":"0.01","rank":"good"},"FCP":{"histogram":[65.79,23.65,10.56],"p75":2139,"rank":"average"},"FID":{"histogram":[90.95,6.38,2.67],"p75":24,"rank":"good"},"LCP":{"histogram":[71.28,20.38,8.33],"p75":2673,"rank":"average"}},{"url":"https://www.ebay.de/","CLS":{"histogram":[87.95,10.92,1.13],"p75":"0.02","rank":"good"},"FCP":{"histogram":[90.92,6.41,2.67],"p75":1095,"rank":"good"},"FID":{"histogram":[90.11,8.08,1.81],"p75":30,"rank":"good"},"LCP":{"histogram":[88.27,8.42,3.31],"p75":1770,"rank":"good"}},{"url":"https://www.bol.com/nl/nl/","CLS":{"histogram":[80.41,16.35,3.24],"p75":"0.02","rank":"good"},"FCP":{"histogram":[94.06,4.4,1.54],"p75":952,"rank":"good"},"FID":{"histogram":[86.54,9.72,3.74],"p75":50,"rank":"good"},"LCP":{"histogram":[92.72,5.6,1.68],"p75":1558,"rank":"good"}},{"url":"https://rozetka.com.ua/","CLS":{"histogram":[58.64,18.96,22.39],"p75":"0.21","rank":"average"},"FCP":{"histogram":[80.01,10.38,9.61],"p75":1579,"rank":"good"},"FID":{"histogram":[83.65,10.29,6.06],"p75":43,"rank":"good"},"LCP":{"histogram":[42.69,26.44,30.87],"p75":4559,"rank":"poor"}},{"url":"https://m.olx.ua/","CLS":{"histogram":[47.56,18.24,34.19],"p75":"0.29","rank":"poor"},"FCP":{"histogram":[67.84,20.15,12.01],"p75":2112,"rank":"average"},"FID":{"histogram":[54.12,11.5,34.38],"p75":650,"rank":"poor"},"LCP":{"histogram":[67.3,19.48,13.22],"p75":2915,"rank":"average"}},{"url":"https://prom.ua/","CLS":{"histogram":[65.12,11.94,22.94],"p75":"0.21","rank":"average"},"FCP":{"histogram":[81.39,11.5,7.11],"p75":1550,"rank":"good"},"FID":{"histogram":[80.75,7.85,11.4],"p75":51,"rank":"good"},"LCP":{"histogram":[77.24,14.45,8.31],"p75":2401,"rank":"good"}},{"url":"https://epicentrk.ua/","CLS":{"histogram":[15.1,3.7,81.21],"p75":"0.90","rank":"poor"},"FCP":{"histogram":[56.53,19.85,23.62],"p75":2925,"rank":"average"},"FID":{"histogram":[50.68,12.05,37.27],"p75":721,"rank":"poor"},"LCP":{"histogram":[33.39,30.73,35.88],"p75":4988,"rank":"poor"}},{"url":"https://merxu.com/pl/","CLS":{"histogram":[89.14,2.45,8.41],"p75":"0.01","rank":"good"},"FCP":{"histogram":[84.92,10.41,4.67],"p75":1418,"rank":"good"},"FID":{"histogram":[84.05,9.53,6.42],"p75":43,"rank":"good"},"LCP":{"histogram":[83,11.85,5.15],"p75":2091,"rank":"good"}},{"url":"https://www.x-kom.pl/","CLS":{"histogram":[28.21,30.19,41.6],"p75":"0.63","rank":"poor"},"FCP":{"histogram":[88.93,6.81,4.25],"p75":1076,"rank":"good"},"FID":{"histogram":[55.44,13.14,31.42],"p75":547,"rank":"poor"},"LCP":{"histogram":[76.94,13.31,9.74],"p75":2379,"rank":"good"}},{"url":"https://www.morele.net/","CLS":{"histogram":[98.64,0.74,0.62],"p75":"0.00","rank":"good"},"FCP":{"histogram":[88.23,7.72,4.05],"p75":1222,"rank":"good"},"FID":{"histogram":[87.51,7.85,4.64],"p75":30,"rank":"good"},"LCP":{"histogram":[90.84,6.47,2.68],"p75":1600,"rank":"good"}},{"url":"https://shopee.pl/","CLS":{"histogram":[16.38,42.83,40.79],"p75":"0.65","rank":"poor"},"FCP":{"histogram":[34.41,40.85,24.74],"p75":3004,"rank":"poor"},"FID":{"histogram":[71.35,12.43,16.22],"p75":135,"rank":"average"},"LCP":{"histogram":[25.54,29.79,44.67],"p75":5282,"rank":"poor"}}]}