{"params":{"formFactor":"PHONE","origin":true,"date":"27.11.2021"},"metrics":[{"url":"https://allegro.pl","CLS":{"histogram":[95.01,3.5,1.49],"p75":"0.01","rank":"good"},"FCP":{"histogram":[91.53,6.09,2.38],"p75":1218,"rank":"good"},"FID":{"histogram":[93.88,5.26,0.87],"p75":40,"rank":"good"},"LCP":{"histogram":[92.16,5.09,2.75],"p75":1533,"rank":"good"}},{"url":"https://m.ceneo.pl","CLS":{"histogram":[78.03,14.78,7.19],"p75":"0.08","rank":"good"},"FCP":{"histogram":[82.8,13.04,4.16],"p75":1549,"rank":"good"},"FID":{"histogram":[88.31,8.96,2.73],"p75":32,"rank":"good"},"LCP":{"histogram":[76.4,15.09,8.5],"p75":2430,"rank":"good"}},{"url":"https://www.mediaexpert.pl","CLS":{"histogram":[71.95,13.71,14.33],"p75":"0.11","rank":"average"},"FCP":{"histogram":[83.28,9.3,7.42],"p75":1364,"rank":"good"},"FID":{"histogram":[83.36,10.64,5.99],"p75":53,"rank":"good"},"LCP":{"histogram":[82.75,10.24,7.01],"p75":1966,"rank":"good"}},{"url":"https://m.euro.com.pl","CLS":{"histogram":[77.26,11.59,11.15],"p75":"0.06","rank":"good"},"FCP":{"histogram":[84.02,11.22,4.75],"p75":1423,"rank":"good"},"FID":{"histogram":[94.27,4.81,0.92],"p75":19,"rank":"good"},"LCP":{"histogram":[83.42,11.48,5.1],"p75":2032,"rank":"good"}},{"url":"https://www.empik.com","CLS":{"histogram":[50.17,26.86,22.96],"p75":"0.22","rank":"average"},"FCP":{"histogram":[77.48,16.62,5.9],"p75":1731,"rank":"good"},"FID":{"histogram":[85.14,9.62,5.24],"p75":50,"rank":"good"},"LCP":{"histogram":[67.98,18.35,13.67],"p75":2930,"rank":"average"}},{"url":"https://www.doz.pl","CLS":{"histogram":[96.29,2.03,1.67],"p75":"0.03","rank":"good"},"FCP":{"histogram":[85.09,10.27,4.64],"p75":1392,"rank":"good"},"FID":{"histogram":[96.32,2.93,0.75],"p75":30,"rank":"good"},"LCP":{"histogram":[90.05,7.06,2.89],"p75":1713,"rank":"good"}},{"url":"https://www.eobuwie.com.pl","CLS":{"histogram":[30.95,21.06,47.99],"p75":"0.37","rank":"poor"},"FCP":{"histogram":[75.47,19.72,4.81],"p75":1789,"rank":"good"},"FID":{"histogram":[93.28,5.48,1.25],"p75":23,"rank":"good"},"LCP":{"histogram":[51.3,27.12,21.58],"p75":3762,"rank":"average"}},{"url":"https://www.amazon.pl","CLS":{"histogram":[76.24,16.76,7],"p75":"0.09","rank":"good"},"FCP":{"histogram":[86.23,9.62,4.15],"p75":1346,"rank":"good"},"FID":{"histogram":[95.25,3.8,0.95],"p75":21,"rank":"good"},"LCP":{"histogram":[90.14,7.22,2.64],"p75":1675,"rank":"good"}},{"url":"https://m.aliexpress.com","CLS":{"histogram":[90.76,6.68,2.56],"p75":"0.02","rank":"good"},"FCP":{"histogram":[85.01,8.8,6.19],"p75":1248,"rank":"good"},"FID":{"histogram":[94.78,4.27,0.94],"p75":30,"rank":"good"},"LCP":{"histogram":[72.09,16.53,11.38],"p75":2679,"rank":"average"}},{"url":"https://www.castorama.pl","CLS":{"histogram":[59.31,7.87,32.83],"p75":"0.43","rank":"poor"},"FCP":{"histogram":[72.6,18.24,9.17],"p75":1897,"rank":"average"},"FID":{"histogram":[86.78,7.6,5.62],"p75":33,"rank":"good"},"LCP":{"histogram":[48.62,27.46,23.93],"p75":3936,"rank":"average"}},{"url":"https://allegrolokalnie.pl","CLS":{"histogram":[66.75,28.13,5.11],"p75":"0.11","rank":"average"},"FCP":{"histogram":[88.09,8.78,3.12],"p75":1331,"rank":"good"},"FID":{"histogram":[93.37,4.59,2.04],"p75":20,"rank":"good"},"LCP":{"histogram":[68.59,20.71,10.7],"p75":2825,"rank":"average"}},{"url":"https://www.zalando.pl","CLS":{"histogram":[80.44,17.27,2.29],"p75":"0.08","rank":"good"},"FCP":{"histogram":[88.79,7.76,3.45],"p75":1184,"rank":"good"},"FID":{"histogram":[76.31,13.55,10.14],"p75":88,"rank":"good"},"LCP":{"histogram":[87.93,8.48,3.59],"p75":1789,"rank":"good"}},{"url":"https://m.olx.pl","CLS":{"histogram":[50.63,18.8,30.57],"p75":"0.31","rank":"poor"},"FCP":{"histogram":[40.21,35.97,23.82],"p75":2985,"rank":"average"},"FID":{"histogram":[69.47,15.09,15.44],"p75":150,"rank":"average"},"LCP":{"histogram":[51.16,27.61,21.22],"p75":3735,"rank":"average"}},{"url":"https://m.alza.cz","CLS":{"histogram":[73.89,8.79,17.32],"p75":"0.11","rank":"average"},"FCP":{"histogram":[68.61,20.13,11.25],"p75":2085,"rank":"average"},"FID":{"histogram":[86.28,9.37,4.35],"p75":39,"rank":"good"},"LCP":{"histogram":[73.36,16.74,9.9],"p75":2608,"rank":"average"}},{"url":"https://www.mall.cz","CLS":{"histogram":[72.92,8.36,18.72],"p75":"0.12","rank":"average"},"FCP":{"histogram":[69.39,23.84,6.77],"p75":1939,"rank":"average"},"FID":{"histogram":[77.45,10.97,11.58],"p75":82,"rank":"good"},"LCP":{"histogram":[75.59,16.53,7.88],"p75":2473,"rank":"good"}},{"url":"https://www.rohlik.cz","CLS":{"histogram":[74.31,5.46,20.23],"p75":"0.10","rank":"good"},"FCP":{"histogram":[75.62,17.95,6.43],"p75":1795,"rank":"good"},"FID":{"histogram":[79.14,10.58,10.28],"p75":65,"rank":"good"},"LCP":{"histogram":[72.56,17.17,10.27],"p75":2647,"rank":"average"}},{"url":"https://www.czc.cz","CLS":{"histogram":[94.86,1.82,3.32],"p75":"0.00","rank":"good"},"FCP":{"histogram":[90.43,6.67,2.9],"p75":1156,"rank":"good"},"FID":{"histogram":[93.47,5.06,1.47],"p75":20,"rank":"good"},"LCP":{"histogram":[88.87,8.13,3],"p75":1762,"rank":"good"}},{"url":"https://m.alza.sk","CLS":{"histogram":[74.96,8.34,16.69],"p75":"0.10","rank":"good"},"FCP":{"histogram":[65.08,20.34,14.59],"p75":2247,"rank":"average"},"FID":{"histogram":[88.41,8.03,3.56],"p75":33,"rank":"good"},"LCP":{"histogram":[72.14,16.96,10.9],"p75":2691,"rank":"average"}},{"url":"https://www.mall.sk","CLS":{"histogram":[72.22,8.84,18.94],"p75":"0.13","rank":"average"},"FCP":{"histogram":[77.61,17.55,4.84],"p75":1743,"rank":"good"},"FID":{"histogram":[81.29,8.78,9.93],"p75":58,"rank":"good"},"LCP":{"histogram":[79.8,13.79,6.41],"p75":2264,"rank":"good"}},{"url":"https://tesco.sk","CLS":{"histogram":[65.09,18.64,16.27],"p75":"0.13","rank":"average"},"FCP":{"histogram":[43.97,29.22,26.8],"p75":3133,"rank":"poor"},"FID":{"histogram":[88.6,7.78,3.63],"p75":39,"rank":"good"},"LCP":{"histogram":[47.99,27.26,24.76],"p75":3983,"rank":"average"}},{"url":"https://www.notino.sk","CLS":{"histogram":[85.31,7.04,7.65],"p75":"0.02","rank":"good"},"FCP":{"histogram":[92.72,4.92,2.35],"p75":945,"rank":"good"},"FID":{"histogram":[93.12,5.2,1.68],"p75":18,"rank":"good"},"LCP":{"histogram":[89.31,7.54,3.15],"p75":1603,"rank":"good"}},{"url":"https://www.amazon.de","CLS":{"histogram":[72.34,20.38,7.28],"p75":"0.11","rank":"average"},"FCP":{"histogram":[93.87,4.01,2.12],"p75":896,"rank":"good"},"FID":{"histogram":[93.28,5.22,1.5],"p75":28,"rank":"good"},"LCP":{"histogram":[93.7,4.51,1.79],"p75":1497,"rank":"good"}},{"url":"https://www.otto.de","CLS":{"histogram":[79.69,11.37,8.94],"p75":"0.07","rank":"good"},"FCP":{"histogram":[95.83,2.89,1.29],"p75":765,"rank":"good"},"FID":{"histogram":[88.32,7.97,3.71],"p75":33,"rank":"good"},"LCP":{"histogram":[88.06,9.32,2.63],"p75":1815,"rank":"good"}},{"url":"https://www.zalando.de","CLS":{"histogram":[94.5,3.15,2.36],"p75":"0.07","rank":"good"},"FCP":{"histogram":[92.32,5.89,1.79],"p75":1065,"rank":"good"},"FID":{"histogram":[75.64,14.77,9.59],"p75":94,"rank":"good"},"LCP":{"histogram":[91.32,6.63,2.06],"p75":1621,"rank":"good"}},{"url":"https://www.mediamarkt.de","CLS":{"histogram":[69.73,12.92,17.35],"p75":"0.14","rank":"average"},"FCP":{"histogram":[68.54,22.06,9.4],"p75":2028,"rank":"average"},"FID":{"histogram":[69.69,13.78,16.53],"p75":155,"rank":"average"},"LCP":{"histogram":[65.08,21.78,13.13],"p75":2987,"rank":"average"}},{"url":"https://www.lidl.de","CLS":{"histogram":[66.1,9.8,24.1],"p75":"0.22","rank":"average"},"FCP":{"histogram":[75.9,17.15,6.94],"p75":1773,"rank":"good"},"FID":{"histogram":[91.58,6.28,2.14],"p75":32,"rank":"good"},"LCP":{"histogram":[72.97,18.48,8.55],"p75":2601,"rank":"average"}},{"url":"https://www.ebay.de","CLS":{"histogram":[84.1,8.7,7.2],"p75":"0.05","rank":"good"},"FCP":{"histogram":[94.14,4.18,1.68],"p75":985,"rank":"good"},"FID":{"histogram":[90.76,8.01,1.23],"p75":36,"rank":"good"},"LCP":{"histogram":[92.68,5.31,2.01],"p75":1570,"rank":"good"}},{"url":"https://www.bol.com","CLS":{"histogram":[88.05,3.46,8.49],"p75":"0.00","rank":"good"},"FCP":{"histogram":[95.56,3.16,1.29],"p75":824,"rank":"good"},"FID":{"histogram":[93.54,4.05,2.4],"p75":30,"rank":"good"},"LCP":{"histogram":[96.19,2.82,0.99],"p75":1179,"rank":"good"}},{"url":"https://rozetka.com.ua","CLS":{"histogram":[72.56,7.85,19.59],"p75":"0.12","rank":"average"},"FCP":{"histogram":[56.81,28.23,14.96],"p75":2421,"rank":"average"},"FID":{"histogram":[77.68,8.89,13.43],"p75":75,"rank":"good"},"LCP":{"histogram":[60.98,19.81,19.21],"p75":3405,"rank":"average"}},{"url":"https://m.olx.ua","CLS":{"histogram":[62.35,14.9,22.76],"p75":"0.21","rank":"average"},"FCP":{"histogram":[45.77,33.43,20.8],"p75":2790,"rank":"average"},"FID":{"histogram":[67.07,16.12,16.81],"p75":171,"rank":"average"},"LCP":{"histogram":[55.99,25.61,18.4],"p75":3465,"rank":"average"}},{"url":"https://prom.ua","CLS":{"histogram":[81.49,8.84,9.67],"p75":"0.04","rank":"good"},"FCP":{"histogram":[16.23,37.81,45.96],"p75":3866,"rank":"poor"},"FID":{"histogram":[76.85,12.34,10.81],"p75":93,"rank":"good"},"LCP":{"histogram":[21.72,37.47,40.81],"p75":4988,"rank":"poor"}},{"url":"https://www.ria.com","CLS":{"histogram":[88.73,5.88,5.38],"p75":"0.04","rank":"good"},"FCP":{"histogram":[78.71,14.42,6.87],"p75":1688,"rank":"good"},"FID":{"histogram":[95.19,4.1,0.7],"p75":23,"rank":"good"},"LCP":{"histogram":[85.59,9.28,5.13],"p75":1991,"rank":"good"}},{"url":"https://epicentrk.ua","CLS":{"histogram":[80.62,8.46,10.91],"p75":"0.08","rank":"good"},"FCP":{"histogram":[53.82,25.9,20.28],"p75":2664,"rank":"average"},"FID":{"histogram":[72.97,14.29,12.74],"p75":120,"rank":"average"},"LCP":{"histogram":[55.28,25.88,18.84],"p75":3549,"rank":"average"}}]}