{"params":{"formFactor":"PHONE","url":true,"collectionPeriod":{"firstDate":{"year":2023,"month":10,"day":24},"lastDate":{"year":2023,"month":11,"day":20}},"date":"22.11.2023"},"metrics":[{"url":"https://allegro.pl/","CLS":{"histogram":[97.41,0.94,1.65],"p75":"0.00","rank":"good"},"FCP":{"histogram":[89.95,6.86,3.19],"p75":1259,"rank":"good"},"FID":{"histogram":[91.09,6.7,2.21],"p75":25,"rank":"good"},"LCP":{"histogram":[91.25,4.73,4.02],"p75":1552,"rank":"good"},"TTFB":{"histogram":[81.29,14.88,3.83],"p75":717,"rank":"good"},"INP":{"histogram":[75.65,19.95,4.4],"p75":196,"rank":"good"}},{"url":"https://m.ceneo.pl/","CLS":{"histogram":[91.52,6.59,1.89],"p75":"0.06","rank":"good"},"FCP":{"histogram":[86.46,7.65,5.89],"p75":1319,"rank":"good"},"FID":{"histogram":[81.16,14.31,4.53],"p75":72,"rank":"good"},"LCP":{"histogram":[84.85,9.08,6.07],"p75":1909,"rank":"good"},"TTFB":{"histogram":[77.63,17.06,5.31],"p75":751,"rank":"good"},"INP":{"histogram":[28.51,49.86,21.63],"p75":462,"rank":"average"}},{"url":"https://www.mediaexpert.pl/","CLS":{"histogram":[89.69,6.73,3.59],"p75":"0.05","rank":"good"},"FCP":{"histogram":[84.92,9.37,5.71],"p75":1355,"rank":"good"},"FID":{"histogram":[82.66,12.59,4.75],"p75":60,"rank":"good"},"LCP":{"histogram":[89.73,5.92,4.36],"p75":1540,"rank":"good"},"TTFB":{"histogram":[85.77,10.58,3.65],"p75":532,"rank":"good"},"INP":{"histogram":[35.41,45.65,18.94],"p75":428,"rank":"average"}},{"url":"https://www.empik.com/","CLS":{"histogram":[55.21,35.35,9.45],"p75":"0.18","rank":"average"},"FCP":{"histogram":[76.01,11.97,12.02],"p75":1769,"rank":"good"},"FID":{"histogram":[50.5,23.25,26.25],"p75":316,"rank":"poor"},"LCP":{"histogram":[67.81,14.02,18.17],"p75":3144,"rank":"average"},"TTFB":{"histogram":[78.73,9.55,11.73],"p75":656,"rank":"good"},"INP":{"histogram":[8.2,27.08,64.73],"p75":1175,"rank":"poor"}},{"url":"https://www.doz.pl/","CLS":{"histogram":[83.35,10.69,5.96],"p75":"0.00","rank":"good"},"FCP":{"histogram":[85.31,9.1,5.59],"p75":1374,"rank":"good"},"FID":{"histogram":[85.22,9.86,4.92],"p75":44,"rank":"good"},"LCP":{"histogram":[86.1,8.45,5.45],"p75":1866,"rank":"good"},"TTFB":{"histogram":[81.36,13.72,4.92],"p75":678,"rank":"good"},"INP":{"histogram":[55.17,34.28,10.55],"p75":307,"rank":"average"}},{"url":"https://www.amazon.pl/","CLS":{"histogram":[97.69,0.73,1.58],"p75":"0.00","rank":"good"},"FCP":{"histogram":[88.18,7.66,4.17],"p75":1199,"rank":"good"},"FID":{"histogram":[93.32,5.76,0.92],"p75":26,"rank":"good"},"LCP":{"histogram":[89.17,6.31,4.52],"p75":1453,"rank":"good"},"TTFB":{"histogram":[82.39,13.8,3.81],"p75":641,"rank":"good"},"INP":{"histogram":[79.24,18.39,2.38],"p75":181,"rank":"good"}},{"url":"https://m.aliexpress.com/","CLS":{"histogram":[59.82,34.51,5.67],"p75":"0.14","rank":"average"},"FCP":{"histogram":[59.37,15.29,25.34],"p75":3014,"rank":"poor"},"FID":{"histogram":[79.54,16.48,3.98],"p75":71,"rank":"good"},"LCP":{"histogram":[51.72,14.19,34.09],"p75":5012,"rank":"poor"},"TTFB":{"histogram":[54.91,27.77,17.32],"p75":1312,"rank":"average"},"INP":{"histogram":[63.17,25.32,11.51],"p75":273,"rank":"average"}},{"url":"https://www.castorama.pl/","CLS":{"histogram":[32.46,3.06,64.48],"p75":"0.57","rank":"poor"},"FCP":{"histogram":[76.26,16.22,7.52],"p75":1773,"rank":"good"},"FID":{"histogram":[62.46,12.96,24.58],"p75":290,"rank":"average"},"LCP":{"histogram":[71.81,17.46,10.73],"p75":2678,"rank":"average"},"TTFB":{"histogram":[63.34,30.12,6.54],"p75":1103,"rank":"average"},"INP":{"histogram":[8.06,27.89,64.06],"p75":1296,"rank":"poor"}},{"url":"https://allegrolokalnie.pl/","CLS":{"histogram":[64.65,29.87,5.47],"p75":"0.12","rank":"average"},"FCP":{"histogram":[93.1,4.14,2.76],"p75":983,"rank":"good"},"FID":{"histogram":[84.14,11.78,4.08],"p75":48,"rank":"good"},"LCP":{"histogram":[67.12,20.68,12.21],"p75":2894,"rank":"average"},"TTFB":{"histogram":[91.07,6.72,2.21],"p75":432,"rank":"good"},"INP":{"histogram":[69.9,23.53,6.58],"p75":226,"rank":"average"}}]}