{"params":{"formFactor":"PHONE","url":true,"collectionPeriod":{"firstDate":{"year":2023,"month":9,"day":10},"lastDate":{"year":2023,"month":10,"day":7}},"date":"9.10.2023"},"metrics":[{"url":"https://allegro.pl/","CLS":{"histogram":[97.1,1.15,1.76],"p75":"0.00","rank":"good"},"FCP":{"histogram":[89.61,6.68,3.71],"p75":1234,"rank":"good"},"FID":{"histogram":[90.94,6.51,2.55],"p75":26,"rank":"good"},"LCP":{"histogram":[90.31,4.76,4.92],"p75":1566,"rank":"good"},"TTFB":{"histogram":[81.82,13.7,4.48],"p75":699,"rank":"good"},"INP":{"histogram":[74.81,20.28,4.9],"p75":200,"rank":"good"}},{"url":"https://m.ceneo.pl/","CLS":{"histogram":[85.59,12.14,2.27],"p75":"0.08","rank":"good"},"FCP":{"histogram":[85.61,9.05,5.33],"p75":1393,"rank":"good"},"FID":{"histogram":[79.9,15.39,4.71],"p75":78,"rank":"good"},"LCP":{"histogram":[83.3,10.62,6.08],"p75":2036,"rank":"good"},"TTFB":{"histogram":[73.61,21.05,5.34],"p75":832,"rank":"average"},"INP":{"histogram":[25.47,51.78,22.75],"p75":477,"rank":"average"}},{"url":"https://www.mediaexpert.pl/","CLS":{"histogram":[88.47,6.48,5.05],"p75":"0.05","rank":"good"},"FCP":{"histogram":[84.33,9.94,5.73],"p75":1399,"rank":"good"},"FID":{"histogram":[79.7,14.21,6.09],"p75":74,"rank":"good"},"LCP":{"histogram":[89.34,5.98,4.69],"p75":1568,"rank":"good"},"TTFB":{"histogram":[85.27,10.82,3.91],"p75":555,"rank":"good"},"INP":{"histogram":[34.92,45.77,19.31],"p75":431,"rank":"average"}},{"url":"https://www.empik.com/","CLS":{"histogram":[48.53,37.38,14.09],"p75":"0.22","rank":"average"},"FCP":{"histogram":[74.5,12.74,12.77],"p75":1845,"rank":"average"},"FID":{"histogram":[55.11,22.39,22.5],"p75":267,"rank":"average"},"LCP":{"histogram":[60.14,16.78,23.08],"p75":3779,"rank":"average"},"TTFB":{"histogram":[75.44,11.87,12.68],"p75":788,"rank":"good"},"INP":{"histogram":[8.68,28.7,62.62],"p75":1101,"rank":"poor"}},{"url":"https://www.doz.pl/","CLS":{"histogram":[89.59,7.19,3.22],"p75":"0.02","rank":"good"},"FCP":{"histogram":[86.77,8.12,5.11],"p75":1312,"rank":"good"},"FID":{"histogram":[84.31,9.85,5.84],"p75":45,"rank":"good"},"LCP":{"histogram":[88.53,6.97,4.5],"p75":1732,"rank":"good"},"TTFB":{"histogram":[82.11,13.15,4.74],"p75":669,"rank":"good"},"INP":{"histogram":[58.06,30.38,11.56],"p75":299,"rank":"average"}},{"url":"https://www.amazon.pl/","CLS":{"histogram":[97.88,0.51,1.61],"p75":"0.00","rank":"good"},"FCP":{"histogram":[87.56,7.94,4.5],"p75":1236,"rank":"good"},"FID":{"histogram":[92.89,6.33,0.78],"p75":28,"rank":"good"},"LCP":{"histogram":[87.45,7.38,5.17],"p75":1642,"rank":"good"},"TTFB":{"histogram":[80.88,15.07,4.05],"p75":678,"rank":"good"},"INP":{"histogram":[76.14,20.84,3.01],"p75":195,"rank":"good"}},{"url":"https://m.aliexpress.com/","CLS":{"histogram":[61.76,32.12,6.12],"p75":"0.14","rank":"average"},"FCP":{"histogram":[60.02,20.05,19.94],"p75":2505,"rank":"average"},"FID":{"histogram":[71.49,19.04,9.47],"p75":127,"rank":"average"},"LCP":{"histogram":[52.14,20.15,27.71],"p75":4233,"rank":"poor"},"TTFB":{"histogram":[52.52,31.2,16.28],"p75":1270,"rank":"average"},"INP":{"histogram":[47.25,33.84,18.91],"p75":378,"rank":"average"}},{"url":"https://www.castorama.pl/","CLS":{"histogram":[38.32,3.95,57.73],"p75":"0.55","rank":"poor"},"FCP":{"histogram":[80.45,13.05,6.49],"p75":1633,"rank":"good"},"FID":{"histogram":[60.69,13.11,26.2],"p75":327,"rank":"poor"},"LCP":{"histogram":[74.76,14.97,10.28],"p75":2521,"rank":"average"},"TTFB":{"histogram":[67.07,27.21,5.72],"p75":995,"rank":"average"},"INP":{"histogram":[13.54,25.18,61.28],"p75":1295,"rank":"poor"}},{"url":"https://allegrolokalnie.pl/","CLS":{"histogram":[59.52,31.62,8.86],"p75":"0.13","rank":"average"},"FCP":{"histogram":[92.69,4.56,2.75],"p75":1016,"rank":"good"},"FID":{"histogram":[85.28,10.75,3.96],"p75":43,"rank":"good"},"LCP":{"histogram":[65.4,21.53,13.07],"p75":2982,"rank":"average"},"TTFB":{"histogram":[89.9,7.84,2.26],"p75":454,"rank":"good"},"INP":{"histogram":[70.34,22.98,6.68],"p75":223,"rank":"average"}},{"url":"https://www.zalando.pl/","CLS":{"histogram":[90.66,1.37,7.96],"p75":"0.00","rank":"good"},"FCP":{"histogram":[80.03,12.68,7.28],"p75":1612,"rank":"good"},"FID":{"histogram":[82.45,13.06,4.49],"p75":62,"rank":"good"},"LCP":{"histogram":[84.03,9.67,6.3],"p75":2016,"rank":"good"},"TTFB":{"histogram":[77.25,18.67,4.08],"p75":765,"rank":"good"},"INP":{"histogram":[57.72,26.87,15.41],"p75":328,"rank":"average"}},{"url":"https://m.olx.pl/","CLS":{"histogram":[60.56,17.57,21.88],"p75":"0.20","rank":"average"},"FCP":{"histogram":[66.99,22.88,10.13],"p75":2058,"rank":"average"},"FID":{"histogram":[46.51,17.46,36.02],"p75":512,"rank":"poor"},"LCP":{"histogram":[71.27,15.01,13.72],"p75":2718,"rank":"average"},"TTFB":{"histogram":[48.78,42.38,8.83],"p75":1169,"rank":"average"},"INP":{"histogram":[15.94,23.66,60.4],"p75":1415,"rank":"poor"}},{"url":"https://m.alza.cz/","CLS":{"histogram":[81.78,9.44,8.78],"p75":"0.06","rank":"good"},"FCP":{"histogram":[85.06,10.86,4.08],"p75":1437,"rank":"good"},"FID":{"histogram":[88.82,8.55,2.63],"p75":33,"rank":"good"},"LCP":{"histogram":[87.39,8.66,3.95],"p75":1824,"rank":"good"},"TTFB":{"histogram":[74.1,22.11,3.79],"p75":816,"rank":"average"},"INP":{"histogram":[63.89,28.42,7.69],"p75":259,"rank":"average"}},{"url":"https://www.mall.cz/","CLS":{"histogram":[67.73,10.58,21.69],"p75":"0.18","rank":"average"},"FCP":{"histogram":[50.4,36.94,12.65],"p75":2347,"rank":"average"},"FID":{"histogram":[45.65,12.02,42.32],"p75":1156,"rank":"poor"},"LCP":{"histogram":[72.47,18.79,8.74],"p75":2592,"rank":"average"},"TTFB":{"histogram":[11.78,69.67,18.55],"p75":1625,"rank":"average"},"INP":{"histogram":[11.92,15.55,72.53],"p75":2642,"rank":"poor"}},{"url":"https://www.rohlik.cz/","CLS":{"histogram":[49.12,8.46,42.42],"p75":"0.51","rank":"poor"},"FCP":{"histogram":[74.57,19.18,6.24],"p75":1814,"rank":"average"},"FID":{"histogram":[72.13,16.52,11.35],"p75":116,"rank":"average"},"LCP":{"histogram":[84.67,11.12,4.21],"p75":2095,"rank":"good"},"TTFB":{"histogram":[57.11,38.19,4.69],"p75":994,"rank":"average"},"INP":{"histogram":[9.21,39.82,50.97],"p75":826,"rank":"poor"}},{"url":"https://www.czc.cz/","CLS":{"histogram":[40.7,53.27,6.03],"p75":"0.20","rank":"average"},"FCP":{"histogram":[92.4,4.98,2.62],"p75":1005,"rank":"good"},"FID":{"histogram":[93.35,5.56,1.09],"p75":24,"rank":"good"},"LCP":{"histogram":[90.35,6.73,2.92],"p75":1670,"rank":"good"},"TTFB":{"histogram":[91.57,6.29,2.14],"p75":415,"rank":"good"},"INP":{"histogram":[54.98,39.17,5.86],"p75":279,"rank":"average"}},{"url":"https://m.alza.sk/","CLS":{"histogram":[82.39,9.44,8.17],"p75":"0.05","rank":"good"},"FCP":{"histogram":[90.19,6.89,2.92],"p75":1204,"rank":"good"},"FID":{"histogram":[90.53,7.37,2.1],"p75":26,"rank":"good"},"LCP":{"histogram":[90.84,6.14,3.02],"p75":1548,"rank":"good"},"TTFB":{"histogram":[77.5,18.88,3.62],"p75":761,"rank":"good"},"INP":{"histogram":[69.5,24.46,6.04],"p75":228,"rank":"average"}},{"url":"https://www.mall.sk/","CLS":{"histogram":[36.07,10.46,53.48],"p75":"0.78","rank":"poor"},"FCP":{"histogram":[70.81,20.89,8.3],"p75":1934,"rank":"average"},"FID":{"histogram":[50.92,14.84,34.24],"p75":515,"rank":"poor"},"LCP":{"histogram":[76.53,15.17,8.3],"p75":2427,"rank":"good"},"TTFB":{"histogram":[37.35,50.48,12.16],"p75":1335,"rank":"average"},"INP":{"histogram":[14.61,23.47,61.91],"p75":1582,"rank":"poor"}},{"url":"https://tesco.sk/","CLS":{"histogram":[51.52,7.8,40.68],"p75":"0.32","rank":"poor"},"FCP":{"histogram":[66.78,24.09,9.13],"p75":2028,"rank":"average"},"FID":{"histogram":[85.95,8.29,5.76],"p75":42,"rank":"good"},"LCP":{"histogram":[66.7,22.86,10.44],"p75":2834,"rank":"average"},"TTFB":{"histogram":[86.04,11.05,2.91],"p75":631,"rank":"good"},"INP":{"histogram":[60.62,24.03,15.35],"p75":319,"rank":"average"}},{"url":"https://www.notino.sk/","CLS":{"histogram":[96.01,2.32,1.68],"p75":"0.00","rank":"good"},"FCP":{"histogram":[82.29,12.07,5.64],"p75":1504,"rank":"good"},"FID":{"histogram":[81.51,13,5.49],"p75":65,"rank":"good"},"LCP":{"histogram":[89.95,6.5,3.55],"p75":1610,"rank":"good"},"TTFB":{"histogram":[85.09,12.09,2.82],"p75":598,"rank":"good"},"INP":{"histogram":[33.22,47.16,19.62],"p75":443,"rank":"average"}},{"url":"https://www.amazon.de/","CLS":{"histogram":[97.11,1.93,0.96],"p75":"0.01","rank":"good"},"FCP":{"histogram":[89.28,7.31,3.41],"p75":1191,"rank":"good"},"FID":{"histogram":[92.32,6.47,1.21],"p75":32,"rank":"good"},"LCP":{"histogram":[92.05,4.99,2.96],"p75":1368,"rank":"good"},"TTFB":{"histogram":[82.49,14.27,3.25],"p75":651,"rank":"good"},"INP":{"histogram":[72.52,23.81,3.68],"p75":210,"rank":"average"}},{"url":"https://www.otto.de/","CLS":{"histogram":[64.76,30.08,5.16],"p75":"0.10","rank":"good"},"FCP":{"histogram":[93.71,4.12,2.17],"p75":906,"rank":"good"},"FID":{"histogram":[84.94,10.95,4.11],"p75":52,"rank":"good"},"LCP":{"histogram":[76.81,15.69,7.5],"p75":2407,"rank":"good"},"TTFB":{"histogram":[95.62,3.07,1.31],"p75":281,"rank":"good"},"INP":{"histogram":[70.96,22.7,6.33],"p75":222,"rank":"average"}},{"url":"https://www.zalando.de/","CLS":{"histogram":[87.87,1.26,10.87],"p75":"0.00","rank":"good"},"FCP":{"histogram":[87.34,8.53,4.13],"p75":1285,"rank":"good"},"FID":{"histogram":[84.77,11.91,3.33],"p75":56,"rank":"good"},"LCP":{"histogram":[89.85,6.7,3.46],"p75":1664,"rank":"good"},"TTFB":{"histogram":[86.03,11.26,2.71],"p75":571,"rank":"good"},"INP":{"histogram":[63.78,23.47,12.76],"p75":285,"rank":"average"}},{"url":"https://www.mediamarkt.de/","CLS":{"histogram":[68.82,5.99,25.19],"p75":"0.25","rank":"average"},"FCP":{"histogram":[81.66,12.09,6.25],"p75":1541,"rank":"good"},"FID":{"histogram":[56.47,21.25,22.28],"p75":260,"rank":"average"},"LCP":{"histogram":[83.63,10.44,5.93],"p75":1989,"rank":"good"},"TTFB":{"histogram":[70.89,22.43,6.69],"p75":893,"rank":"average"},"INP":{"histogram":[4.66,20.7,74.64],"p75":1836,"rank":"poor"}},{"url":"https://www.lidl.de/","CLS":{"histogram":[95.65,2.99,1.37],"p75":"0.00","rank":"good"},"FCP":{"histogram":[59.1,24.77,16.13],"p75":2438,"rank":"average"},"FID":{"histogram":[87,9.03,3.98],"p75":39,"rank":"good"},"LCP":{"histogram":[63.37,20.89,15.74],"p75":3165,"rank":"average"},"TTFB":{"histogram":[72.55,22.06,5.39],"p75":853,"rank":"average"},"INP":{"histogram":[51.18,37.7,11.12],"p75":324,"rank":"average"}},{"url":"https://www.ebay.de/","CLS":{"histogram":[99.48,0.43,0.1],"p75":"0.00","rank":"good"},"FCP":{"histogram":[90.77,6.55,2.68],"p75":1080,"rank":"good"},"FID":{"histogram":[91.91,6.55,1.54],"p75":26,"rank":"good"},"LCP":{"histogram":[91.85,5.82,2.32],"p75":1561,"rank":"good"},"TTFB":{"histogram":[78.94,15.76,5.3],"p75":731,"rank":"good"},"INP":{"histogram":[66.77,27.08,6.16],"p75":243,"rank":"average"}},{"url":"https://www.bol.com/nl/nl/","CLS":{"histogram":[91.64,6.46,1.9],"p75":"0.01","rank":"good"},"FCP":{"histogram":[93.07,5.22,1.71],"p75":1033,"rank":"good"},"FID":{"histogram":[89.99,7.58,2.43],"p75":36,"rank":"good"},"LCP":{"histogram":[93.55,4.97,1.48],"p75":1474,"rank":"good"},"TTFB":{"histogram":[88.67,9.85,1.48],"p75":568,"rank":"good"},"INP":{"histogram":[77.25,17.59,5.16],"p75":189,"rank":"good"}},{"url":"https://rozetka.com.ua/","CLS":{"histogram":[78.21,10.28,11.51],"p75":"0.08","rank":"good"},"FCP":{"histogram":[83.56,10.28,6.16],"p75":1453,"rank":"good"},"FID":{"histogram":[79.71,12.28,8.01],"p75":64,"rank":"good"},"LCP":{"histogram":[54.2,21.14,24.66],"p75":3993,"rank":"average"},"TTFB":{"histogram":[75.76,18.82,5.42],"p75":789,"rank":"good"},"INP":{"histogram":[27.63,48.27,24.1],"p75":485,"rank":"average"}},{"url":"https://m.olx.ua/","CLS":{"histogram":[66.19,23.74,10.07],"p75":"0.15","rank":"average"},"FCP":{"histogram":[66.26,22.66,11.08],"p75":2116,"rank":"average"},"FID":{"histogram":[39.76,16.63,43.61],"p75":673,"rank":"poor"},"LCP":{"histogram":[69.46,18.92,11.63],"p75":2784,"rank":"average"},"TTFB":{"histogram":[43,39.55,17.45],"p75":1506,"rank":"average"},"INP":{"histogram":[13.29,19.18,67.53],"p75":1797,"rank":"poor"}},{"url":"https://prom.ua/","CLS":{"histogram":[40.76,29.9,29.34],"p75":"0.39","rank":"poor"},"FCP":{"histogram":[69.42,21.32,9.26],"p75":1983,"rank":"average"},"FID":{"histogram":[64.87,16.09,19.04],"p75":199,"rank":"average"},"LCP":{"histogram":[66.22,21.11,12.67],"p75":2951,"rank":"average"},"TTFB":{"histogram":[46.2,41.14,12.65],"p75":1326,"rank":"average"},"INP":{"histogram":[9.66,36.88,53.46],"p75":929,"rank":"poor"}},{"url":"https://www.ria.com/","CLS":{"histogram":[97.82,1.51,0.67],"p75":"0.00","rank":"good"},"FCP":{"histogram":[79.51,13.97,6.52],"p75":1635,"rank":"good"},"FID":{"histogram":[95.88,3.34,0.78],"p75":25,"rank":"good"},"LCP":{"histogram":[87.14,8.16,4.69],"p75":1808,"rank":"good"},"TTFB":{"histogram":[66.88,24.33,8.79],"p75":1008,"rank":"average"},"INP":{"histogram":[78.23,19.22,2.55],"p75":190,"rank":"good"}},{"url":"https://epicentrk.ua/","CLS":{"histogram":[8.46,9,82.54],"p75":"0.89","rank":"poor"},"FCP":{"histogram":[77.96,15.89,6.15],"p75":1717,"rank":"good"},"FID":{"histogram":[81.17,14.92,3.92],"p75":71,"rank":"good"},"LCP":{"histogram":[47.58,31.37,21.05],"p75":3729,"rank":"average"},"TTFB":{"histogram":[68.12,25.24,6.64],"p75":932,"rank":"average"},"INP":{"histogram":[11.6,51.56,36.83],"p75":599,"rank":"poor"}},{"url":"https://merxu.com/pl/","CLS":{"histogram":[82.87,3.25,13.88],"p75":"0.03","rank":"good"},"FCP":{"histogram":[80.32,15.62,4.06],"p75":1679,"rank":"good"},"FID":{"histogram":[84.44,5.01,10.54],"p75":20,"rank":"good"},"LCP":{"histogram":[85.11,11.5,3.39],"p75":2082,"rank":"good"},"TTFB":{"histogram":[69.12,28.55,2.33],"p75":909,"rank":"average"},"INP":{"histogram":[49.39,29.68,20.93],"p75":406,"rank":"average"}},{"url":"https://www.x-kom.pl/","CLS":{"histogram":[28.03,23.92,48.05],"p75":"0.66","rank":"poor"},"FCP":{"histogram":[85.91,8.32,5.77],"p75":1334,"rank":"good"},"FID":{"histogram":[33.75,15.87,50.38],"p75":1301,"rank":"poor"},"LCP":{"histogram":[82.69,9.24,8.07],"p75":1979,"rank":"good"},"TTFB":{"histogram":[86.22,10.29,3.49],"p75":525,"rank":"good"},"INP":{"histogram":[2.85,3.37,93.78],"p75":3761,"rank":"poor"}},{"url":"https://www.morele.net/","CLS":{"histogram":[52.98,46.2,0.82],"p75":"0.13","rank":"average"},"FCP":{"histogram":[90.47,6.18,3.35],"p75":1040,"rank":"good"},"FID":{"histogram":[91.15,7.09,1.76],"p75":22,"rank":"good"},"LCP":{"histogram":[93.35,4.59,2.06],"p75":1331,"rank":"good"},"TTFB":{"histogram":[82.33,13.06,4.62],"p75":651,"rank":"good"},"INP":{"histogram":[66.29,27.95,5.76],"p75":247,"rank":"average"}}]}