{"params":{"formFactor":"PHONE","url":true,"collectionPeriod":{"firstDate":{"year":2025,"month":1,"day":7},"lastDate":{"year":2025,"month":2,"day":3}},"date":"5.02.2025"},"metrics":[{"url":"www.zalando.de/","CLS":{"histogram":[83.77,10.08,6.15],"p75":"0.00","rank":"good"},"FCP":{"histogram":[84.5,10.48,5.03],"p75":1387,"rank":"good"},"LCP":{"histogram":[91.77,5.25,2.99],"p75":1413,"rank":"good"},"TTFB":{"histogram":[90.58,7.53,1.89],"p75":442,"rank":"good"},"INP":{"histogram":[83.61,13.6,2.79],"p75":158,"rank":"good"},"minimalGood":83.61},{"url":"allegro.pl/","CLS":{"histogram":[99.21,0.25,0.54],"p75":"0.00","rank":"good"},"FCP":{"histogram":[89.41,7.25,3.33],"p75":1212,"rank":"good"},"LCP":{"histogram":[92.73,4.73,2.54],"p75":1448,"rank":"good"},"TTFB":{"histogram":[82.96,14.08,2.97],"p75":680,"rank":"good"},"INP":{"histogram":[84.52,12.63,2.85],"p75":154,"rank":"good"},"minimalGood":82.96},{"url":"allegrolokalnie.pl/","CLS":{"histogram":[89.06,10.16,0.78],"p75":"0.02","rank":"good"},"FCP":{"histogram":[94.47,3.39,2.14],"p75":826,"rank":"good"},"LCP":{"histogram":[85.91,9.16,4.92],"p75":1883,"rank":"good"},"TTFB":{"histogram":[92.09,5.9,2.01],"p75":399,"rank":"good"},"INP":{"histogram":[82.27,13.45,4.29],"p75":156,"rank":"good"},"minimalGood":82.27},{"url":"www.lidl.de/","CLS":{"histogram":[96.28,2.25,1.47],"p75":"0.05","rank":"good"},"FCP":{"histogram":[83.64,11.49,4.87],"p75":1427,"rank":"good"},"LCP":{"histogram":[85.05,9.74,5.21],"p75":1880,"rank":"good"},"TTFB":{"histogram":[81.46,15.19,3.35],"p75":647,"rank":"good"},"INP":{"histogram":[82.41,15.3,2.29],"p75":164,"rank":"good"},"minimalGood":81.46},{"url":"www.amazon.de/","CLS":{"histogram":[94.99,4.21,0.8],"p75":"0.00","rank":"good"},"FCP":{"histogram":[88.88,7.6,3.51],"p75":1160,"rank":"good"},"LCP":{"histogram":[91.89,5.4,2.71],"p75":1312,"rank":"good"},"TTFB":{"histogram":[81.25,15.13,3.62],"p75":673,"rank":"good"},"INP":{"histogram":[81.76,15.09,3.15],"p75":166,"rank":"good"},"minimalGood":81.25},{"url":"merxu.com/pl/","CLS":{"histogram":[87.51,2.46,10.03],"p75":"0.03","rank":"good"},"FCP":{"histogram":[89.15,6.63,4.22],"p75":1456,"rank":"good"},"LCP":{"histogram":[80.56,14.19,5.24],"p75":2246,"rank":"good"},"TTFB":{"histogram":[],"p75":"-","rank":"-"},"INP":{"histogram":[],"p75":"-","rank":"-"},"minimalGood":80.56},{"url":"www.amazon.pl/","CLS":{"histogram":[96.49,2.4,1.11],"p75":"0.00","rank":"good"},"FCP":{"histogram":[86.7,8.04,5.27],"p75":1241,"rank":"good"},"LCP":{"histogram":[88.25,6.87,4.89],"p75":1490,"rank":"good"},"TTFB":{"histogram":[78.95,15.84,5.2],"p75":720,"rank":"good"},"INP":{"histogram":[80.22,16.41,3.37],"p75":172,"rank":"good"},"minimalGood":78.95},{"url":"www.zalando.pl/","CLS":{"histogram":[84.24,9.52,6.24],"p75":"0.00","rank":"good"},"FCP":{"histogram":[78.02,13.68,8.29],"p75":1666,"rank":"good"},"LCP":{"histogram":[87.47,7.37,5.16],"p75":1712,"rank":"good"},"TTFB":{"histogram":[86.3,10.99,2.71],"p75":565,"rank":"good"},"INP":{"histogram":[77.79,18.32,3.89],"p75":186,"rank":"good"},"minimalGood":77.79},{"url":"www.ebay.de/","CLS":{"histogram":[98.97,0.74,0.29],"p75":"0.00","rank":"good"},"FCP":{"histogram":[91.35,5.84,2.81],"p75":1064,"rank":"good"},"LCP":{"histogram":[91.89,5.81,2.3],"p75":1638,"rank":"good"},"TTFB":{"histogram":[80.87,15.22,3.91],"p75":678,"rank":"good"},"INP":{"histogram":[69.57,21.3,9.13],"p75":239,"rank":"average"},"minimalGood":69.57},{"url":"www.otto.de/","CLS":{"histogram":[68.61,21.53,9.86],"p75":"0.10","rank":"good"},"FCP":{"histogram":[92.49,5.15,2.36],"p75":904,"rank":"good"},"LCP":{"histogram":[84.69,10.25,5.07],"p75":1947,"rank":"good"},"TTFB":{"histogram":[92.74,5.58,1.69],"p75":339,"rank":"good"},"INP":{"histogram":[80.58,15.54,3.88],"p75":170,"rank":"good"},"minimalGood":68.61},{"url":"www.doz.pl/","CLS":{"histogram":[72.45,22.25,5.3],"p75":"0.15","rank":"average"},"FCP":{"histogram":[82.73,10.75,6.53],"p75":1471,"rank":"good"},"LCP":{"histogram":[87.77,7.54,4.68],"p75":1762,"rank":"good"},"TTFB":{"histogram":[80.43,14.32,5.25],"p75":680,"rank":"good"},"INP":{"histogram":[67.93,25.85,6.22],"p75":233,"rank":"average"},"minimalGood":67.93},{"url":"www.ria.com/","CLS":{"histogram":[98.4,0.42,1.17],"p75":"0.00","rank":"good"},"FCP":{"histogram":[77.18,14.4,8.43],"p75":1711,"rank":"good"},"LCP":{"histogram":[85.15,8.84,6.01],"p75":1865,"rank":"good"},"TTFB":{"histogram":[63.47,23.35,13.18],"p75":1234,"rank":"average"},"INP":{"histogram":[91.98,6.52,1.49],"p75":125,"rank":"good"},"minimalGood":63.47},{"url":"www.mediaexpert.pl/","CLS":{"histogram":[86.6,8.98,4.42],"p75":"0.06","rank":"good"},"FCP":{"histogram":[87.83,7.42,4.75],"p75":1149,"rank":"good"},"LCP":{"histogram":[91.02,5.27,3.71],"p75":1373,"rank":"good"},"TTFB":{"histogram":[84.27,11.48,4.24],"p75":555,"rank":"good"},"INP":{"histogram":[63.45,29.49,7.05],"p75":271,"rank":"average"},"minimalGood":63.45},{"url":"www.morele.net/","CLS":{"histogram":[61.95,37.27,0.78],"p75":"0.13","rank":"average"},"FCP":{"histogram":[91.09,5.16,3.75],"p75":978,"rank":"good"},"LCP":{"histogram":[94,2.73,3.28],"p75":1148,"rank":"good"},"TTFB":{"histogram":[82.47,12.83,4.7],"p75":630,"rank":"good"},"INP":{"histogram":[77.68,18.98,3.35],"p75":187,"rank":"good"},"minimalGood":61.95},{"url":"m.alza.cz/","CLS":{"histogram":[60,28.19,11.81],"p75":"0.12","rank":"average"},"FCP":{"histogram":[92.59,5.16,2.25],"p75":981,"rank":"good"},"LCP":{"histogram":[80.7,13.11,6.19],"p75":2206,"rank":"good"},"TTFB":{"histogram":[92.09,6.24,1.67],"p75":454,"rank":"good"},"INP":{"histogram":[74.02,21.43,4.55],"p75":204,"rank":"average"},"minimalGood":60},{"url":"m.alza.sk/","CLS":{"histogram":[59.61,27.94,12.45],"p75":"0.12","rank":"average"},"FCP":{"histogram":[94.14,4.21,1.65],"p75":879,"rank":"good"},"LCP":{"histogram":[84.44,10.6,4.96],"p75":1999,"rank":"good"},"TTFB":{"histogram":[90.21,8.01,1.78],"p75":505,"rank":"good"},"INP":{"histogram":[80.26,16.35,3.39],"p75":173,"rank":"good"},"minimalGood":59.61},{"url":"www.notino.sk/","CLS":{"histogram":[94,3.26,2.74],"p75":"0.01","rank":"good"},"FCP":{"histogram":[88.41,8.61,2.98],"p75":1231,"rank":"good"},"LCP":{"histogram":[79.44,13.19,7.37],"p75":2259,"rank":"good"},"TTFB":{"histogram":[80.55,16.28,3.17],"p75":707,"rank":"good"},"INP":{"histogram":[57.35,35.84,6.81],"p75":266,"rank":"average"},"minimalGood":57.35},{"url":"rozetka.com.ua/","CLS":{"histogram":[73.07,10.4,16.53],"p75":"0.11","rank":"average"},"FCP":{"histogram":[79.16,14.36,6.47],"p75":1666,"rank":"good"},"LCP":{"histogram":[87.86,7.29,4.85],"p75":1798,"rank":"good"},"TTFB":{"histogram":[65.21,28.82,5.97],"p75":943,"rank":"average"},"INP":{"histogram":[54.75,28.66,16.59],"p75":349,"rank":"average"},"minimalGood":54.75},{"url":"tesco.sk/","CLS":{"histogram":[51,9.06,39.94],"p75":"1.00","rank":"poor"},"FCP":{"histogram":[81.55,13.21,5.24],"p75":1584,"rank":"good"},"LCP":{"histogram":[82.26,12.56,5.17],"p75":2156,"rank":"good"},"TTFB":{"histogram":[92.91,5.38,1.72],"p75":336,"rank":"good"},"INP":{"histogram":[81.12,15.35,3.53],"p75":170,"rank":"good"},"minimalGood":51},{"url":"www.bol.com/nl/nl/","CLS":{"histogram":[82.73,15.5,1.77],"p75":"0.00","rank":"good"},"FCP":{"histogram":[90.48,7.39,2.12],"p75":1185,"rank":"good"},"LCP":{"histogram":[95.46,3.38,1.16],"p75":1260,"rank":"good"},"TTFB":{"histogram":[89.84,8.63,1.53],"p75":466,"rank":"good"},"INP":{"histogram":[45.33,38.73,15.94],"p75":375,"rank":"average"},"minimalGood":45.33},{"url":"www.empik.com/","CLS":{"histogram":[48.62,35.92,15.46],"p75":"0.21","rank":"average"},"FCP":{"histogram":[88.37,7.39,4.24],"p75":1163,"rank":"good"},"LCP":{"histogram":[71.06,12.69,16.24],"p75":2892,"rank":"average"},"TTFB":{"histogram":[85.28,11.44,3.28],"p75":591,"rank":"good"},"INP":{"histogram":[43.36,43.45,13.19],"p75":352,"rank":"average"},"minimalGood":43.36},{"url":"m.olx.ua/","CLS":{"histogram":[59.05,22.13,18.82],"p75":"0.21","rank":"average"},"FCP":{"histogram":[73.83,18.48,7.68],"p75":1839,"rank":"average"},"LCP":{"histogram":[78.45,12.37,9.18],"p75":2307,"rank":"good"},"TTFB":{"histogram":[45.53,41.48,12.99],"p75":1348,"rank":"average"},"INP":{"histogram":[42.32,30.94,26.74],"p75":528,"rank":"poor"},"minimalGood":42.32},{"url":"prom.ua/","CLS":{"histogram":[42.74,22.77,34.49],"p75":"0.31","rank":"poor"},"FCP":{"histogram":[73.48,20.89,5.63],"p75":1834,"rank":"average"},"LCP":{"histogram":[85.21,10.4,4.39],"p75":2055,"rank":"good"},"TTFB":{"histogram":[41.47,49.97,8.56],"p75":1257,"rank":"average"},"INP":{"histogram":[50.33,34.12,15.55],"p75":352,"rank":"average"},"minimalGood":41.47},{"url":"m.olx.pl/","CLS":{"histogram":[48,22.71,29.29],"p75":"0.32","rank":"poor"},"FCP":{"histogram":[69.05,21.28,9.67],"p75":1987,"rank":"average"},"LCP":{"histogram":[74.23,13.02,12.75],"p75":2543,"rank":"average"},"TTFB":{"histogram":[40.96,46.1,12.95],"p75":1364,"rank":"average"},"INP":{"histogram":[51.64,30.76,17.6],"p75":379,"rank":"average"},"minimalGood":40.96},{"url":"www.mall.sk/","CLS":{"histogram":[22.01,12.02,65.97],"p75":"0.94","rank":"poor"},"FCP":{"histogram":[78.44,15.76,5.79],"p75":1700,"rank":"good"},"LCP":{"histogram":[85.92,9.99,4.09],"p75":1973,"rank":"good"},"TTFB":{"histogram":[39.15,51.64,9.2],"p75":1251,"rank":"average"},"INP":{"histogram":[20.01,34.03,45.97],"p75":1201,"rank":"poor"},"minimalGood":20.01},{"url":"www.mediamarkt.de/","CLS":{"histogram":[49.35,23.31,27.34],"p75":"0.28","rank":"poor"},"FCP":{"histogram":[84.74,10.78,4.48],"p75":1389,"rank":"good"},"LCP":{"histogram":[85.48,7.92,6.6],"p75":1775,"rank":"good"},"TTFB":{"histogram":[83.36,12.77,3.87],"p75":624,"rank":"good"},"INP":{"histogram":[15.95,27.19,56.86],"p75":1252,"rank":"poor"},"minimalGood":15.95},{"url":"www.mall.cz/","CLS":{"histogram":[41.09,20.47,38.44],"p75":"0.45","rank":"poor"},"FCP":{"histogram":[78.41,15,6.59],"p75":1694,"rank":"good"},"LCP":{"histogram":[86.89,9.09,4.02],"p75":1897,"rank":"good"},"TTFB":{"histogram":[43.17,47.57,9.26],"p75":1195,"rank":"average"},"INP":{"histogram":[15.37,31.67,52.97],"p75":1361,"rank":"poor"},"minimalGood":15.37},{"url":"epicentrk.ua/","CLS":{"histogram":[78.75,15.85,5.4],"p75":"0.08","rank":"good"},"FCP":{"histogram":[82.59,11.49,5.92],"p75":1464,"rank":"good"},"LCP":{"histogram":[39.17,33.2,27.63],"p75":4200,"rank":"poor"},"TTFB":{"histogram":[75.01,17.36,7.64],"p75":800,"rank":"good"},"INP":{"histogram":[15.17,41.87,42.97],"p75":1290,"rank":"poor"},"minimalGood":15.17},{"url":"www.rohlik.cz/","CLS":{"histogram":[54.99,12.56,32.46],"p75":"0.34","rank":"poor"},"FCP":{"histogram":[87.18,9.74,3.08],"p75":1337,"rank":"good"},"LCP":{"histogram":[91.69,5.49,2.82],"p75":1485,"rank":"good"},"TTFB":{"histogram":[87.64,10.07,2.29],"p75":570,"rank":"good"},"INP":{"histogram":[14.75,36.63,48.62],"p75":1034,"rank":"poor"},"minimalGood":14.75},{"url":"www.x-kom.pl/","CLS":{"histogram":[45.47,10.99,43.54],"p75":"0.63","rank":"poor"},"FCP":{"histogram":[80.97,12.04,6.99],"p75":1540,"rank":"good"},"LCP":{"histogram":[84.86,8.79,6.35],"p75":1854,"rank":"good"},"TTFB":{"histogram":[80.79,12.07,7.14],"p75":640,"rank":"good"},"INP":{"histogram":[14.09,31.13,54.78],"p75":1120,"rank":"poor"},"minimalGood":14.09},{"url":"www.castorama.pl/","CLS":{"histogram":[31.31,1.66,67.03],"p75":"0.61","rank":"poor"},"FCP":{"histogram":[70.27,19.46,10.28],"p75":1984,"rank":"average"},"LCP":{"histogram":[61.5,20.82,17.68],"p75":3320,"rank":"average"},"TTFB":{"histogram":[40.88,43.68,15.44],"p75":1329,"rank":"average"},"INP":{"histogram":[7.35,25,67.65],"p75":1247,"rank":"poor"},"minimalGood":7.35}]}