{"params":{"formFactor":"PHONE","url":true,"collectionPeriod":{"firstDate":{"year":2024,"month":6,"day":1},"lastDate":{"year":2024,"month":6,"day":28}},"date":"30.06.2024"},"metrics":[{"url":"www.muzo.fm/","CLS":{"histogram":[99.71,0.07,0.22],"p75":"0.00","rank":"good"},"FCP":{"histogram":[86.1,8.28,5.62],"p75":1290,"rank":"good"},"FID":{"histogram":[97.66,1.89,0.45],"p75":15,"rank":"good"},"LCP":{"histogram":[85.09,8.69,6.22],"p75":1885,"rank":"good"},"TTFB":{"histogram":[91.37,5.3,3.33],"p75":360,"rank":"good"},"INP":{"histogram":[95.6,3.49,0.91],"p75":93,"rank":"good"},"minimalGood":85.09},{"url":"www.voxfm.pl/","CLS":{"histogram":[99.56,0.18,0.26],"p75":"0.00","rank":"good"},"FCP":{"histogram":[78.17,12.7,9.13],"p75":1676,"rank":"good"},"FID":{"histogram":[90.59,7.59,1.82],"p75":33,"rank":"good"},"LCP":{"histogram":[79.07,11.76,9.17],"p75":2245,"rank":"good"},"TTFB":{"histogram":[81.71,12.87,5.42],"p75":622,"rank":"good"},"INP":{"histogram":[85.11,11.34,3.55],"p75":143,"rank":"good"},"minimalGood":78.17},{"url":"www.rmf.fm/","CLS":{"histogram":[94.23,1.14,4.62],"p75":"0.00","rank":"good"},"FCP":{"histogram":[85.72,8.73,5.55],"p75":1334,"rank":"good"},"FID":{"histogram":[89.07,8.91,2.03],"p75":42,"rank":"good"},"LCP":{"histogram":[77.77,12.77,9.46],"p75":2353,"rank":"good"},"TTFB":{"histogram":[83.94,10.93,5.12],"p75":599,"rank":"good"},"INP":{"histogram":[79.45,15.85,4.7],"p75":176,"rank":"good"},"minimalGood":77.77},{"url":"radio357.pl/","CLS":{"histogram":[98.22,0.34,1.43],"p75":"0.03","rank":"good"},"FCP":{"histogram":[75.73,15.63,8.64],"p75":1792,"rank":"good"},"FID":{"histogram":[92.78,5.39,1.84],"p75":24,"rank":"good"},"LCP":{"histogram":[78.05,13.5,8.45],"p75":2325,"rank":"good"},"TTFB":{"histogram":[89.3,7.3,3.4],"p75":453,"rank":"good"},"INP":{"histogram":[73.92,21.64,4.43],"p75":205,"rank":"average"},"minimalGood":73.92},{"url":"www.antyradio.pl/","CLS":{"histogram":[95.94,3.26,0.8],"p75":"0.04","rank":"good"},"FCP":{"histogram":[87.18,7.99,4.83],"p75":1265,"rank":"good"},"FID":{"histogram":[84.98,11.32,3.69],"p75":46,"rank":"good"},"LCP":{"histogram":[84.14,9.88,5.98],"p75":1930,"rank":"good"},"TTFB":{"histogram":[94.53,3.4,2.08],"p75":224,"rank":"good"},"INP":{"histogram":[68.99,22.28,8.72],"p75":237,"rank":"average"},"minimalGood":68.99},{"url":"www.tokfm.pl/Tokfm/0,0.html","CLS":{"histogram":[66.84,19.05,14.11],"p75":"0.12","rank":"average"},"FCP":{"histogram":[86.45,8.33,5.22],"p75":1323,"rank":"good"},"FID":{"histogram":[89.63,7.98,2.39],"p75":26,"rank":"good"},"LCP":{"histogram":[87.23,5.99,6.78],"p75":1603,"rank":"good"},"TTFB":{"histogram":[86.04,9.67,4.28],"p75":559,"rank":"good"},"INP":{"histogram":[73.79,21.34,4.87],"p75":205,"rank":"average"},"minimalGood":66.84},{"url":"www.rmfclassic.pl/","CLS":{"histogram":[91.18,2.23,6.58],"p75":"0.03","rank":"good"},"FCP":{"histogram":[80.03,12.06,7.91],"p75":1576,"rank":"good"},"FID":{"histogram":[87.28,9.91,2.81],"p75":44,"rank":"good"},"LCP":{"histogram":[57.57,21.64,20.79],"p75":3628,"rank":"average"},"TTFB":{"histogram":[85.89,9.57,4.55],"p75":545,"rank":"good"},"INP":{"histogram":[59.47,28.12,12.41],"p75":302,"rank":"average"},"minimalGood":57.57},{"url":"www.radiozet.pl/","CLS":{"histogram":[76.12,20.34,3.53],"p75":"0.08","rank":"good"},"FCP":{"histogram":[82.34,11.11,6.55],"p75":1515,"rank":"good"},"FID":{"histogram":[89.99,7.69,2.32],"p75":32,"rank":"good"},"LCP":{"histogram":[58.48,20.35,21.17],"p75":3624,"rank":"average"},"TTFB":{"histogram":[92.26,5.13,2.61],"p75":335,"rank":"good"},"INP":{"histogram":[55.84,34.93,9.23],"p75":290,"rank":"average"},"minimalGood":55.84},{"url":"wnet.fm/","CLS":{"histogram":[48,5.06,46.94],"p75":"0.56","rank":"poor"},"FCP":{"histogram":[73.37,16.18,10.45],"p75":1882,"rank":"average"},"FID":{"histogram":[87.3,8.91,3.79],"p75":33,"rank":"good"},"LCP":{"histogram":[63.02,20.29,16.69],"p75":3189,"rank":"average"},"TTFB":{"histogram":[77.53,16.83,5.63],"p75":735,"rank":"good"},"INP":{"histogram":[79.3,13.14,7.56],"p75":160,"rank":"good"},"minimalGood":48},{"url":"www.radiomaryja.pl/","CLS":{"histogram":[45.48,41.94,12.58],"p75":"0.17","rank":"average"},"FCP":{"histogram":[81.84,9.5,8.66],"p75":1428,"rank":"good"},"FID":{"histogram":[85.28,7.88,6.85],"p75":26,"rank":"good"},"LCP":{"histogram":[53.91,19.67,26.42],"p75":4203,"rank":"poor"},"TTFB":{"histogram":[85.51,8.11,6.38],"p75":528,"rank":"good"},"INP":{"histogram":[76.16,14.89,8.95],"p75":191,"rank":"good"},"minimalGood":45.48},{"url":"www.polskieradio.pl/","CLS":{"histogram":[78.07,12.27,9.66],"p75":"0.08","rank":"good"},"FCP":{"histogram":[42.8,27.18,30.03],"p75":3409,"rank":"poor"},"FID":{"histogram":[89.17,8.5,2.33],"p75":31,"rank":"good"},"LCP":{"histogram":[54.99,23.21,21.8],"p75":3722,"rank":"average"},"TTFB":{"histogram":[68.32,23.61,8.07],"p75":947,"rank":"average"},"INP":{"histogram":[70.59,21.82,7.59],"p75":221,"rank":"average"},"minimalGood":42.8},{"url":"polskieradio24.pl/","CLS":{"histogram":[39.55,35.78,24.67],"p75":"0.24","rank":"average"},"FCP":{"histogram":[84.48,9.3,6.21],"p75":1395,"rank":"good"},"FID":{"histogram":[90.73,6.39,2.87],"p75":23,"rank":"good"},"LCP":{"histogram":[86.56,7.35,6.09],"p75":1726,"rank":"good"},"TTFB":{"histogram":[88.7,7.74,3.55],"p75":458,"rank":"good"},"INP":{"histogram":[77.24,17.09,5.67],"p75":189,"rank":"good"},"minimalGood":39.55},{"url":"nowyswiat.online/","CLS":{"histogram":[89.02,5.59,5.39],"p75":"0.06","rank":"good"},"FCP":{"histogram":[63.88,19.79,16.33],"p75":2294,"rank":"average"},"FID":{"histogram":[92.58,5.78,1.64],"p75":28,"rank":"good"},"LCP":{"histogram":[34.5,26.39,39.12],"p75":5478,"rank":"poor"},"TTFB":{"histogram":[58.72,28.69,12.59],"p75":1158,"rank":"average"},"INP":{"histogram":[63.33,29.54,7.13],"p75":259,"rank":"average"},"minimalGood":34.5}]}