{"params":{"formFactor":"PHONE","url":true,"collectionPeriod":{"firstDate":{"year":2025,"month":8,"day":23},"lastDate":{"year":2025,"month":9,"day":19}},"date":"21.09.2025"},"metrics":[{"url":"www.voxfm.pl/","CLS":{"histogram":[98.97,0.35,0.67],"p75":"0.00","rank":"good"},"FCP":{"histogram":[79.83,10.65,9.52],"p75":1557,"rank":"good"},"LCP":{"histogram":[82.87,8.49,8.64],"p75":1923,"rank":"good"},"TTFB":{"histogram":[81.49,10.96,7.55],"p75":596,"rank":"good"},"INP":{"histogram":[83.93,12.58,3.49],"p75":145,"rank":"good"},"RTT":{"histogram":[32.33,55.96,11.71],"p75":141,"rank":"average"},"minimalGood":82.87},{"url":"radio357.pl/","CLS":{"histogram":[92.44,6.43,1.13],"p75":"0.02","rank":"good"},"FCP":{"histogram":[80.54,11.04,8.42],"p75":1517,"rank":"good"},"LCP":{"histogram":[84.33,9.06,6.61],"p75":1881,"rank":"good"},"TTFB":{"histogram":[85.82,8.57,5.61],"p75":462,"rank":"good"},"INP":{"histogram":[82.36,14.75,2.89],"p75":161,"rank":"good"},"RTT":{"histogram":[48.02,44.98,7],"p75":116,"rank":"average"},"minimalGood":82.36},{"url":"www.antyradio.pl/","CLS":{"histogram":[98.07,1.67,0.26],"p75":"0.03","rank":"good"},"FCP":{"histogram":[79.56,10.68,9.76],"p75":1581,"rank":"good"},"LCP":{"histogram":[78.61,11.71,9.68],"p75":2256,"rank":"good"},"TTFB":{"histogram":[86.94,7.33,5.73],"p75":424,"rank":"good"},"INP":{"histogram":[77.42,18.03,4.54],"p75":186,"rank":"good"},"RTT":{"histogram":[40.76,46.93,12.31],"p75":129,"rank":"average"},"minimalGood":77.42},{"url":"www.rmf.fm/","CLS":{"histogram":[92.93,2.58,4.5],"p75":"0.00","rank":"good"},"FCP":{"histogram":[86.05,7.54,6.41],"p75":1219,"rank":"good"},"LCP":{"histogram":[74.93,13.9,11.17],"p75":2499,"rank":"good"},"TTFB":{"histogram":[81.19,11.54,7.27],"p75":625,"rank":"good"},"INP":{"histogram":[76.55,19.26,4.19],"p75":192,"rank":"good"},"RTT":{"histogram":[35.13,53.94,10.93],"p75":137,"rank":"average"},"minimalGood":74.93},{"url":"www.radiozet.pl/","CLS":{"histogram":[96.53,1.86,1.61],"p75":"0.00","rank":"good"},"FCP":{"histogram":[83.22,9.65,7.12],"p75":1412,"rank":"good"},"LCP":{"histogram":[83.62,9.33,7.05],"p75":1912,"rank":"good"},"TTFB":{"histogram":[89.76,6.17,4.07],"p75":370,"rank":"good"},"INP":{"histogram":[65.07,29.62,5.31],"p75":238,"rank":"average"},"RTT":{"histogram":[44.12,45.7,10.18],"p75":121,"rank":"average"},"minimalGood":65.07},{"url":"wnet.fm/","CLS":{"histogram":[54.36,2.12,43.53],"p75":"0.56","rank":"poor"},"FCP":{"histogram":[80.24,10.85,8.91],"p75":1575,"rank":"good"},"LCP":{"histogram":[70.76,16.66,12.59],"p75":2756,"rank":"average"},"TTFB":{"histogram":[80.58,14.22,5.2],"p75":638,"rank":"good"},"INP":{"histogram":[82.86,13.18,3.96],"p75":151,"rank":"good"},"RTT":{"histogram":[41.48,50.02,8.5],"p75":128,"rank":"average"},"minimalGood":54.36},{"url":"www.radiomaryja.pl/","CLS":{"histogram":[53.39,32.88,13.73],"p75":"0.17","rank":"average"},"FCP":{"histogram":[84.88,7.42,7.7],"p75":1212,"rank":"good"},"LCP":{"histogram":[73.94,12.41,13.65],"p75":2594,"rank":"average"},"TTFB":{"histogram":[84.24,8.99,6.76],"p75":502,"rank":"good"},"INP":{"histogram":[85.34,11.07,3.59],"p75":137,"rank":"good"},"RTT":{"histogram":[43.49,48.05,8.46],"p75":120,"rank":"average"},"minimalGood":53.39},{"url":"www.rmfclassic.pl/","CLS":{"histogram":[89.68,1.7,8.61],"p75":"0.05","rank":"good"},"FCP":{"histogram":[82.9,9.25,7.84],"p75":1397,"rank":"good"},"LCP":{"histogram":[62.96,19.8,17.24],"p75":3245,"rank":"average"},"TTFB":{"histogram":[85.35,9.26,5.39],"p75":494,"rank":"good"},"INP":{"histogram":[53,35.32,11.68],"p75":310,"rank":"average"},"RTT":{"histogram":[44.62,48.02,7.35],"p75":114,"rank":"average"},"minimalGood":53},{"url":"polskieradio24.pl/","CLS":{"histogram":[44.41,27.8,27.79],"p75":"0.25","rank":"average"},"FCP":{"histogram":[79.57,9.5,10.93],"p75":1525,"rank":"good"},"LCP":{"histogram":[72.26,14.18,13.57],"p75":2679,"rank":"average"},"TTFB":{"histogram":[81.73,9.2,9.07],"p75":563,"rank":"good"},"INP":{"histogram":[87.16,10.7,2.14],"p75":139,"rank":"good"},"RTT":{"histogram":[47.12,44.81,8.07],"p75":117,"rank":"average"},"minimalGood":44.41},{"url":"nowyswiat.online/","CLS":{"histogram":[87.57,7.07,5.36],"p75":"0.07","rank":"good"},"FCP":{"histogram":[53.64,17.73,28.64],"p75":3424,"rank":"poor"},"LCP":{"histogram":[35.81,23.34,40.85],"p75":5994,"rank":"poor"},"TTFB":{"histogram":[39.82,29.34,30.83],"p75":2446,"rank":"poor"},"INP":{"histogram":[66.82,26.3,6.88],"p75":243,"rank":"average"},"RTT":{"histogram":[44.64,47.89,7.47],"p75":120,"rank":"average"},"minimalGood":35.81}]}