{"params":{"formFactor":"PHONE","origin":true,"date":"11.12.2021"},"metrics":[{"url":"https://www.rmf.fm","CLS":{"histogram":[41.9,8.88,49.22],"p75":"0.37","rank":"poor"},"FCP":{"histogram":[62.83,21.78,15.39],"p75":2347,"rank":"average"},"FID":{"histogram":[87.06,8.62,4.33],"p75":27,"rank":"good"},"LCP":{"histogram":[70.92,15.73,13.35],"p75":2806,"rank":"average"}},{"url":"https://www.radiozet.pl","CLS":{"histogram":[69.13,19.46,11.41],"p75":"0.10","rank":"good"},"FCP":{"histogram":[69.31,19.89,10.8],"p75":2055,"rank":"average"},"FID":{"histogram":[76.32,12.78,10.9],"p75":90,"rank":"good"},"LCP":{"histogram":[75.35,13.96,10.69],"p75":2517,"rank":"average"}},{"url":"https://www.polskieradio.pl","CLS":{"histogram":[90.66,4.45,4.89],"p75":"0.02","rank":"good"},"FCP":{"histogram":[31.34,37.5,31.16],"p75":3355,"rank":"poor"},"FID":{"histogram":[90.44,7.47,2.09],"p75":24,"rank":"good"},"LCP":{"histogram":[52.67,28.68,18.65],"p75":3495,"rank":"average"}},{"url":"https://www.voxfm.pl","CLS":{"histogram":[63.42,6.57,30.01],"p75":"0.29","rank":"poor"},"FCP":{"histogram":[69.94,14.38,15.68],"p75":2148,"rank":"average"},"FID":{"histogram":[83.14,12.21,4.65],"p75":59,"rank":"good"},"LCP":{"histogram":[34.69,28.19,37.12],"p75":5185,"rank":"poor"}},{"url":"https://www.tokfm.pl","CLS":{"histogram":[49.43,45.94,4.64],"p75":"0.13","rank":"average"},"FCP":{"histogram":[82.91,11.16,5.93],"p75":1528,"rank":"good"},"FID":{"histogram":[88.88,8.52,2.6],"p75":31,"rank":"good"},"LCP":{"histogram":[89.5,5.95,4.55],"p75":1640,"rank":"good"}},{"url":"https://www.antyradio.pl","CLS":{"histogram":[54.9,34.92,10.18],"p75":"0.12","rank":"average"},"FCP":{"histogram":[69.44,20.41,10.15],"p75":2054,"rank":"average"},"FID":{"histogram":[81.53,12.32,6.15],"p75":59,"rank":"good"},"LCP":{"histogram":[69.9,18.56,11.54],"p75":2795,"rank":"average"}},{"url":"https://www.rmfclassic.pl","CLS":{"histogram":[82.81,7.99,9.2],"p75":"0.06","rank":"good"},"FCP":{"histogram":[78.18,13.73,8.1],"p75":1685,"rank":"good"},"FID":{"histogram":[86.4,8.43,5.18],"p75":42,"rank":"good"},"LCP":{"histogram":[79.5,12.56,7.94],"p75":2269,"rank":"good"}},{"url":"https://www.radiomaryja.pl","CLS":{"histogram":[91.32,4.33,4.35],"p75":"0.00","rank":"good"},"FCP":{"histogram":[47.9,22.25,29.85],"p75":3397,"rank":"poor"},"FID":{"histogram":[91.13,5.89,2.98],"p75":24,"rank":"good"},"LCP":{"histogram":[54.7,22.73,22.57],"p75":3823,"rank":"average"}},{"url":"https://polskieradio24.pl","CLS":{"histogram":[74.72,2.88,22.4],"p75":"0.10","rank":"good"},"FCP":{"histogram":[45.9,32.95,21.15],"p75":2806,"rank":"average"},"FID":{"histogram":[93.61,4.68,1.71],"p75":17,"rank":"good"},"LCP":{"histogram":[58.13,25.59,16.28],"p75":3272,"rank":"average"}},{"url":"https://wnet.fm","CLS":{"histogram":[94.26,3.49,2.26],"p75":"0.04","rank":"good"},"FCP":{"histogram":[68.49,19.93,11.58],"p75":2057,"rank":"average"},"FID":{"histogram":[92.91,4.72,2.36],"p75":18,"rank":"good"},"LCP":{"histogram":[77.56,14.02,8.43],"p75":2382,"rank":"good"}},{"url":"https://www.muzo.fm","CLS":{"histogram":[99.16,0.46,0.39],"p75":"0.00","rank":"good"},"FCP":{"histogram":[79.15,12.81,8.04],"p75":1634,"rank":"good"},"FID":{"histogram":[96.27,2.82,0.91],"p75":18,"rank":"good"},"LCP":{"histogram":[78.91,12.93,8.16],"p75":2295,"rank":"good"}},{"url":"https://radio357.pl","CLS":{"histogram":[90.14,5.64,4.22],"p75":"0.05","rank":"good"},"FCP":{"histogram":[68.35,19.4,12.25],"p75":2099,"rank":"average"},"FID":{"histogram":[80.54,10.38,9.08],"p75":60,"rank":"good"},"LCP":{"histogram":[63.52,21.89,14.59],"p75":3122,"rank":"average"}},{"url":"https://nowyswiat.online","CLS":{"histogram":[72.09,8.27,19.64],"p75":"0.12","rank":"average"},"FCP":{"histogram":[30.46,40.2,29.34],"p75":3273,"rank":"poor"},"FID":{"histogram":[74.49,15.99,9.52],"p75":102,"rank":"average"},"LCP":{"histogram":[42.46,32.96,24.59],"p75":4002,"rank":"poor"}}]}