{"params":{"formFactor":"PHONE","url":true,"collectionPeriod":{"firstDate":{"year":2023,"month":11,"day":23},"lastDate":{"year":2023,"month":12,"day":20}},"date":"22.12.2023"},"metrics":[{"url":"https://www.rmf.fm/","CLS":{"histogram":[80.49,1.24,18.27],"p75":"0.05","rank":"good"},"FCP":{"histogram":[79.95,12.59,7.46],"p75":1621,"rank":"good"},"FID":{"histogram":[89.71,8.4,1.89],"p75":38,"rank":"good"},"LCP":{"histogram":[71.08,13.83,15.08],"p75":2824,"rank":"average"},"TTFB":{"histogram":[87.55,8.37,4.08],"p75":510,"rank":"good"},"INP":{"histogram":[78.23,16.29,5.47],"p75":179,"rank":"good"}},{"url":"https://www.radiozet.pl/","CLS":{"histogram":[88.95,8.73,2.32],"p75":"0.08","rank":"good"},"FCP":{"histogram":[81.18,12.71,6.11],"p75":1573,"rank":"good"},"FID":{"histogram":[87.96,9.06,2.98],"p75":40,"rank":"good"},"LCP":{"histogram":[70.32,17.21,12.47],"p75":2780,"rank":"average"},"TTFB":{"histogram":[91.66,5.92,2.42],"p75":369,"rank":"good"},"INP":{"histogram":[47.18,40.63,12.19],"p75":346,"rank":"average"}},{"url":"https://www.polskieradio.pl/","CLS":{"histogram":[96.79,2.46,0.75],"p75":"0.00","rank":"good"},"FCP":{"histogram":[37.54,28.99,33.47],"p75":3549,"rank":"poor"},"FID":{"histogram":[90.06,7.65,2.29],"p75":24,"rank":"good"},"LCP":{"histogram":[51.22,26.4,22.37],"p75":3820,"rank":"average"},"TTFB":{"histogram":[70.29,22.85,6.86],"p75":901,"rank":"average"},"INP":{"histogram":[71.74,21.56,6.69],"p75":218,"rank":"average"}},{"url":"https://www.voxfm.pl/","CLS":{"histogram":[99.37,0.27,0.36],"p75":"0.00","rank":"good"},"FCP":{"histogram":[82.53,10.59,6.88],"p75":1496,"rank":"good"},"FID":{"histogram":[89.38,8.3,2.31],"p75":33,"rank":"good"},"LCP":{"histogram":[81.84,11.07,7.1],"p75":2119,"rank":"good"},"TTFB":{"histogram":[88.77,7.33,3.91],"p75":463,"rank":"good"},"INP":{"histogram":[60.9,23.5,15.61],"p75":360,"rank":"average"}},{"url":"https://www.tokfm.pl/Tokfm/0,0.html","CLS":{"histogram":[63.59,21.14,15.26],"p75":"0.13","rank":"average"},"FCP":{"histogram":[83.29,11.08,5.63],"p75":1486,"rank":"good"},"FID":{"histogram":[91.17,7.01,1.82],"p75":23,"rank":"good"},"LCP":{"histogram":[78.38,10.43,11.19],"p75":2227,"rank":"good"},"TTFB":{"histogram":[88.59,8.51,2.9],"p75":518,"rank":"good"},"INP":{"histogram":[55.72,32.78,11.5],"p75":312,"rank":"average"}},{"url":"https://www.antyradio.pl/","CLS":{"histogram":[93.7,4.96,1.34],"p75":"0.04","rank":"good"},"FCP":{"histogram":[83.79,10.36,5.85],"p75":1483,"rank":"good"},"FID":{"histogram":[87.29,9.61,3.1],"p75":41,"rank":"good"},"LCP":{"histogram":[77.1,13.28,9.61],"p75":2396,"rank":"good"},"TTFB":{"histogram":[92.67,4.79,2.54],"p75":314,"rank":"good"},"INP":{"histogram":[52.11,32.67,15.22],"p75":365,"rank":"average"}},{"url":"https://www.rmfclassic.pl/","CLS":{"histogram":[77.52,2.36,20.12],"p75":"0.07","rank":"good"},"FCP":{"histogram":[86.14,8.92,4.94],"p75":1344,"rank":"good"},"FID":{"histogram":[86.66,10.12,3.22],"p75":43,"rank":"good"},"LCP":{"histogram":[55.37,22.98,21.65],"p75":3701,"rank":"average"},"TTFB":{"histogram":[91.15,6.04,2.81],"p75":447,"rank":"good"},"INP":{"histogram":[51.85,32.86,15.29],"p75":342,"rank":"average"}},{"url":"https://www.radiomaryja.pl/","CLS":{"histogram":[46.69,37.26,16.05],"p75":"0.17","rank":"average"},"FCP":{"histogram":[81.95,9.73,8.32],"p75":1439,"rank":"good"},"FID":{"histogram":[85.13,8.4,6.47],"p75":30,"rank":"good"},"LCP":{"histogram":[52.78,18.91,28.31],"p75":4400,"rank":"poor"},"TTFB":{"histogram":[86.83,6.83,6.34],"p75":474,"rank":"good"},"INP":{"histogram":[72.78,18.57,8.65],"p75":213,"rank":"average"}},{"url":"https://polskieradio24.pl/","CLS":{"histogram":[75.38,0.54,24.08],"p75":"0.08","rank":"good"},"FCP":{"histogram":[50.31,26.27,23.42],"p75":2903,"rank":"average"},"FID":{"histogram":[94.4,4.46,1.15],"p75":16,"rank":"good"},"LCP":{"histogram":[58.62,22.12,19.26],"p75":3480,"rank":"average"},"TTFB":{"histogram":[85.84,10.67,3.49],"p75":612,"rank":"good"},"INP":{"histogram":[62.15,30.76,7.09],"p75":257,"rank":"average"}},{"url":"https://wnet.fm/","CLS":{"histogram":[44.66,4.53,50.8],"p75":"0.56","rank":"poor"},"FCP":{"histogram":[76.28,15.13,8.59],"p75":1742,"rank":"good"},"FID":{"histogram":[86.59,9.43,3.97],"p75":40,"rank":"good"},"LCP":{"histogram":[64.61,20.31,15.08],"p75":3085,"rank":"average"},"TTFB":{"histogram":[84.52,9.04,6.44],"p75":562,"rank":"good"},"INP":{"histogram":[71.16,17.92,10.92],"p75":238,"rank":"average"}},{"url":"https://www.muzo.fm/","CLS":{"histogram":[99.84,0.04,0.12],"p75":"0.00","rank":"good"},"FCP":{"histogram":[87.57,8.01,4.43],"p75":1259,"rank":"good"},"FID":{"histogram":[97.54,2.01,0.46],"p75":15,"rank":"good"},"LCP":{"histogram":[86.46,8.79,4.76],"p75":1873,"rank":"good"},"TTFB":{"histogram":[93.73,3.9,2.37],"p75":326,"rank":"good"},"INP":{"histogram":[94.97,4.25,0.78],"p75":98,"rank":"good"}},{"url":"https://radio357.pl/","CLS":{"histogram":[69.74,24.71,5.55],"p75":"0.12","rank":"average"},"FCP":{"histogram":[80.39,12.66,6.95],"p75":1604,"rank":"good"},"FID":{"histogram":[92.59,5.81,1.6],"p75":20,"rank":"good"},"LCP":{"histogram":[88.66,6.56,4.78],"p75":1677,"rank":"good"},"TTFB":{"histogram":[91.17,5.98,2.85],"p75":393,"rank":"good"},"INP":{"histogram":[66.08,29.73,4.19],"p75":238,"rank":"average"}},{"url":"https://nowyswiat.online/","CLS":{"histogram":[84.63,7.76,7.61],"p75":"0.06","rank":"good"},"FCP":{"histogram":[52.13,19.38,28.49],"p75":3717,"rank":"poor"},"FID":{"histogram":[90.28,7.67,2.05],"p75":32,"rank":"good"},"LCP":{"histogram":[23.16,24.79,52.05],"p75":8311,"rank":"poor"},"TTFB":{"histogram":[42.94,29.69,27.36],"p75":2144,"rank":"poor"},"INP":{"histogram":[54.43,35.35,10.23],"p75":306,"rank":"average"}}]}